{
  "cnn_fear_greed": {
    "score": 60,
    "rating": "greed",
    "previous_close": 59,
    "available": true
  },
  "crypto_fear_greed": {
    "score": 34,
    "rating": "Fear",
    "available": true
  },
  "assets": {
    "gold": {
      "name": "Gold",
      "symbol": "GC=F",
      "price": 4506.6,
      "previous_close": 0,
      "change": 0,
      "change_percent": 0,
      "available": true
    },
    "silver": {
      "name": "Silver",
      "symbol": "SI=F",
      "price": 76.64,
      "previous_close": 0,
      "change": 0,
      "change_percent": 0,
      "available": true
    },
    "bitcoin": {
      "name": "Bitcoin",
      "symbol": "BTC-USD",
      "price": 75772.96,
      "previous_close": 0,
      "change": 0,
      "change_percent": 0,
      "available": true
    },
    "ethereum": {
      "name": "Ethereum",
      "symbol": "ETH-USD",
      "price": 2058.59,
      "previous_close": 0,
      "change": 0,
      "change_percent": 0,
      "available": true
    }
  },
  "last_updated": "2026-05-26T17:35:17.738714"
}