{
  "timestamp": "2025-12-17T21:39:42.000657",
  "scan_mode": "all",
  "hot_stocks": [
    {
      "symbol": "PRH",
      "last_close": 24.73,
      "sma150": 24.73,
      "distance_percent": 0.01,
      "atr": 0.15,
      "atr_percent": 0.61,
      "last_volume": 30260,
      "avg_volume_14d": 28928,
      "golden_cross": false,
      "death_cross": false
    },
    {
      "symbol": "BNJ",
      "last_close": 15.19,
      "sma150": 15.19,
      "distance_percent": 0.02,
      "atr": 0.18,
      "atr_percent": 1.17,
      "last_volume": 8732,
      "avg_volume_14d": 14535,
      "golden_cross": false,
      "death_cross": false
    },
    {
      "symbol": "BCE",
      "last_close": 23.15,
      "sma150": 23.14,
      "distance_percent": 0.03,
      "atr": 0.4,
      "atr_percent": 1.72,
      "last_volume": 2514488,
      "avg_volume_14d": 2873092,
      "golden_cross": false,
      "death_cross": false
    },
    {
      "symbol": "NI",
      "last_close": 41.25,
      "sma150": 41.24,
      "distance_percent": 0.03,
      "atr": 0.69,
      "atr_percent": 1.65,
      "last_volume": 2985717,
      "avg_volume_14d": 2996864,
      "golden_cross": false,
      "death_cross": false
    },
    {
      "symbol": "TTWO",
      "last_close": 240.55,
      "sma150": 240.48,
      "distance_percent": 0.03,
      "atr": 4.26,
      "atr_percent": 1.73,
      "last_volume": 1516629,
      "avg_volume_14d": 1278357,
      "golden_cross": false,
      "death_cross": false
    },
    {
      "symbol": "TPH",
      "last_close": 32.83,
      "sma150": 32.82,
      "distance_percent": 0.04,
      "atr": 0.78,
      "atr_percent": 2.32,
      "last_volume": 782475,
      "avg_volume_14d": 861478,
      "golden_cross": false,
      "death_cross": false
    },
    {
      "symbol": "MCHP",
      "last_close": 63.99,
      "sma150": 63.95,
      "distance_percent": 0.06,
      "atr": 2.45,
      "atr_percent": 3.84,
      "last_volume": 8149356,
      "avg_volume_14d": 9593014,
      "golden_cross": false,
      "death_cross": false
    },
    {
      "symbol": "TAL",
      "last_close": 10.97,
      "sma150": 10.96,
      "distance_percent": 0.08,
      "atr": 0.28,
      "atr_percent": 2.53,
      "last_volume": 2035083,
      "avg_volume_14d": 2633435,
      "golden_cross": false,
      "death_cross": false
    },
    {
      "symbol": "CMSA",
      "last_close": 21.98,
      "sma150": 21.96,
      "distance_percent": 0.08,
      "atr": 0.2,
      "atr_percent": 0.89,
      "last_volume": 37679,
      "avg_volume_14d": 20392,
      "golden_cross": false,
      "death_cross": false
    },
    {
      "symbol": "ATHS",
      "last_close": 25.05,
      "sma150": 25.03,
      "distance_percent": 0.09,
      "atr": 0.09,
      "atr_percent": 0.34,
      "last_volume": 24261,
      "avg_volume_14d": 50150,
      "golden_cross": false,
      "death_cross": false
    },
    {
      "symbol": "SOJE",
      "last_close": 17.92,
      "sma150": 17.9,
      "distance_percent": 0.12,
      "atr": 0.13,
      "atr_percent": 0.72,
      "last_volume": 72047,
      "avg_volume_14d": 83214,
      "golden_cross": false,
      "death_cross": false
    },
    {
      "symbol": "PFH",
      "last_close": 17.43,
      "sma150": 17.4,
      "distance_percent": 0.15,
      "atr": 0.14,
      "atr_percent": 0.79,
      "last_volume": 60893,
      "avg_volume_14d": 49721,
      "golden_cross": false,
      "death_cross": false
    },
    {
      "symbol": "ITW",
      "last_close": 252.4,
      "sma150": 251.92,
      "distance_percent": 0.19,
      "atr": 3.7,
      "atr_percent": 1.47,
      "last_volume": 894792,
      "avg_volume_14d": 1006714,
      "golden_cross": false,
      "death_cross": false
    },
    {
      "symbol": "CVX",
      "last_close": 149.52,
      "sma150": 149.13,
      "distance_percent": 0.26,
      "atr": 2.26,
      "atr_percent": 1.5,
      "last_volume": 8304048,
      "avg_volume_14d": 8570964,
      "golden_cross": false,
      "death_cross": false
    },
    {
      "symbol": "DGX",
      "last_close": 179.1,
      "sma150": 178.62,
      "distance_percent": 0.27,
      "atr": 2.85,
      "atr_percent": 1.56,
      "last_volume": 916503,
      "avg_volume_14d": 961185,
      "golden_cross": false,
      "death_cross": false
    },
    {
      "symbol": "MSM",
      "last_close": 86.1,
      "sma150": 85.84,
      "distance_percent": 0.3,
      "atr": 2.24,
      "atr_percent": 2.64,
      "last_volume": 278187,
      "avg_volume_14d": 628121,
      "golden_cross": false,
      "death_cross": false
    },
    {
      "symbol": "ENB",
      "last_close": 46.94,
      "sma150": 46.79,
      "distance_percent": 0.33,
      "atr": 0.75,
      "atr_percent": 1.56,
      "last_volume": 2654453,
      "avg_volume_14d": 3369800,
      "golden_cross": false,
      "death_cross": false
    },
    {
      "symbol": "NTAP",
      "last_close": 110.96,
      "sma150": 110.58,
      "distance_percent": 0.34,
      "atr": 2.82,
      "atr_percent": 2.44,
      "last_volume": 1781855,
      "avg_volume_14d": 1997985,
      "golden_cross": false,
      "death_cross": false
    },
    {
      "symbol": "BEP",
      "last_close": 26.7,
      "sma150": 26.6,
      "distance_percent": 0.37,
      "atr": 0.62,
      "atr_percent": 2.21,
      "last_volume": 988945,
      "avg_volume_14d": 640107,
      "golden_cross": false,
      "death_cross": false
    },
    {
      "symbol": "VIV",
      "last_close": 11.88,
      "sma150": 11.83,
      "distance_percent": 0.41,
      "atr": 0.28,
      "atr_percent": 2.21,
      "last_volume": 561001,
      "avg_volume_14d": 908628,
      "golden_cross": false,
      "death_cross": false
    },
    {
      "symbol": "SGHC",
      "last_close": 11.39,
      "sma150": 11.34,
      "distance_percent": 0.44,
      "atr": 0.46,
      "atr_percent": 4.1,
      "last_volume": 2190530,
      "avg_volume_14d": 2590342,
      "golden_cross": false,
      "death_cross": false
    },
    {
      "symbol": "CNQ",
      "last_close": 31.86,
      "sma150": 31.72,
      "distance_percent": 0.44,
      "atr": 0.74,
      "atr_percent": 2.21,
      "last_volume": 7406377,
      "avg_volume_14d": 7266907,
      "golden_cross": false,
      "death_cross": false
    },
    {
      "symbol": "BEPH",
      "last_close": 15.38,
      "sma150": 15.31,
      "distance_percent": 0.45,
      "atr": 0.17,
      "atr_percent": 1.09,
      "last_volume": 43633,
      "avg_volume_14d": 21478,
      "golden_cross": false,
      "death_cross": false
    },
    {
      "symbol": "ZETA",
      "last_close": 17.39,
      "sma150": 17.31,
      "distance_percent": 0.47,
      "atr": 0.8,
      "atr_percent": 4.3,
      "last_volume": 4579740,
      "avg_volume_14d": 4470007,
      "golden_cross": false,
      "death_cross": false
    },
    {
      "symbol": "IBKR",
      "last_close": 62.45,
      "sma150": 62.16,
      "distance_percent": 0.47,
      "atr": 1.77,
      "atr_percent": 2.75,
      "last_volume": 3852241,
      "avg_volume_14d": 3773642,
      "golden_cross": false,
      "death_cross": false
    },
    {
      "symbol": "CCL",
      "last_close": 28.03,
      "sma150": 27.88,
      "distance_percent": 0.55,
      "atr": 0.74,
      "atr_percent": 2.79,
      "last_volume": 16266226,
      "avg_volume_14d": 18516957,
      "golden_cross": false,
      "death_cross": false
    },
    {
      "symbol": "RJF",
      "last_close": 161.01,
      "sma150": 160.12,
      "distance_percent": 0.55,
      "atr": 2.69,
      "atr_percent": 1.67,
      "last_volume": 1099880,
      "avg_volume_14d": 1183578,
      "golden_cross": false,
      "death_cross": false
    },
    {
      "symbol": "SHEL",
      "last_close": 71.55,
      "sma150": 71.14,
      "distance_percent": 0.57,
      "atr": 0.81,
      "atr_percent": 1.11,
      "last_volume": 4637755,
      "avg_volume_14d": 3616979,
      "golden_cross": false,
      "death_cross": false
    },
    {
      "symbol": "AN",
      "last_close": 206.61,
      "sma150": 205.4,
      "distance_percent": 0.59,
      "atr": 5.29,
      "atr_percent": 2.49,
      "last_volume": 299385,
      "avg_volume_14d": 384742,
      "golden_cross": false,
      "death_cross": false
    },
    {
      "symbol": "PKG",
      "last_close": 202.33,
      "sma150": 201.13,
      "distance_percent": 0.6,
      "atr": 4.68,
      "atr_percent": 2.34,
      "last_volume": 675108,
      "avg_volume_14d": 846921,
      "golden_cross": false,
      "death_cross": false
    },
    {
      "symbol": "BEPI",
      "last_close": 16.12,
      "sma150": 16.02,
      "distance_percent": 0.65,
      "atr": 0.16,
      "atr_percent": 0.98,
      "last_volume": 18817,
      "avg_volume_14d": 11342,
      "golden_cross": false,
      "death_cross": false
    },
    {
      "symbol": "AEG",
      "last_close": 7.46,
      "sma150": 7.41,
      "distance_percent": 0.68,
      "atr": 0.09,
      "atr_percent": 1.16,
      "last_volume": 3168262,
      "avg_volume_14d": 6177742,
      "golden_cross": false,
      "death_cross": false
    },
    {
      "symbol": "WPC",
      "last_close": 65.15,
      "sma150": 64.68,
      "distance_percent": 0.73,
      "atr": 0.99,
      "atr_percent": 1.49,
      "last_volume": 1201570,
      "avg_volume_14d": 1280942,
      "golden_cross": false,
      "death_cross": false
    },
    {
      "symbol": "USAC",
      "last_close": 23.67,
      "sma150": 23.49,
      "distance_percent": 0.75,
      "atr": 0.68,
      "atr_percent": 2.78,
      "last_volume": 135319,
      "avg_volume_14d": 245600,
      "golden_cross": false,
      "death_cross": false
    },
    {
      "symbol": "ARES",
      "last_close": 168.51,
      "sma150": 167.26,
      "distance_percent": 0.75,
      "atr": 4.83,
      "atr_percent": 2.88,
      "last_volume": 2599181,
      "avg_volume_14d": 6375707,
      "golden_cross": false,
      "death_cross": false
    },
    {
      "symbol": "KKR",
      "last_close": 132.15,
      "sma150": 131.14,
      "distance_percent": 0.77,
      "atr": 4.15,
      "atr_percent": 3.16,
      "last_volume": 2722749,
      "avg_volume_14d": 4122342,
      "golden_cross": false,
      "death_cross": false
    },
    {
      "symbol": "VAL",
      "last_close": 49.63,
      "sma150": 49.24,
      "distance_percent": 0.78,
      "atr": 2.45,
      "atr_percent": 4.33,
      "last_volume": 1974421,
      "avg_volume_14d": 1048457,
      "golden_cross": false,
      "death_cross": false
    },
    {
      "symbol": "ES",
      "last_close": 67.28,
      "sma150": 66.73,
      "distance_percent": 0.82,
      "atr": 1.17,
      "atr_percent": 1.75,
      "last_volume": 2324854,
      "avg_volume_14d": 2301050,
      "golden_cross": false,
      "death_cross": false
    },
    {
      "symbol": "VMC",
      "last_close": 285.41,
      "sma150": 282.98,
      "distance_percent": 0.86,
      "atr": 5.95,
      "atr_percent": 2.02,
      "last_volume": 1618336,
      "avg_volume_14d": 826542,
      "golden_cross": false,
      "death_cross": false
    },
    {
      "symbol": "LAZ",
      "last_close": 50.39,
      "sma150": 49.96,
      "distance_percent": 0.87,
      "atr": 1.85,
      "atr_percent": 3.6,
      "last_volume": 799995,
      "avg_volume_14d": 1044985,
      "golden_cross": false,
      "death_cross": false
    },
    {
      "symbol": "PRS",
      "last_close": 24.02,
      "sma150": 23.81,
      "distance_percent": 0.87,
      "atr": 0.19,
      "atr_percent": 0.78,
      "last_volume": 48132,
      "avg_volume_14d": 37542,
      "golden_cross": false,
      "death_cross": false
    },
    {
      "symbol": "ENO",
      "last_close": 22.75,
      "sma150": 22.55,
      "distance_percent": 0.89,
      "atr": 0.2,
      "atr_percent": 0.9,
      "last_volume": 1698,
      "avg_volume_14d": 6742,
      "golden_cross": false,
      "death_cross": false
    },
    {
      "symbol": "AB",
      "last_close": 39.36,
      "sma150": 39.0,
      "distance_percent": 0.92,
      "atr": 0.86,
      "atr_percent": 2.11,
      "last_volume": 192604,
      "avg_volume_14d": 225807,
      "golden_cross": false,
      "death_cross": false
    },
    {
      "symbol": "TIMB",
      "last_close": 20.7,
      "sma150": 20.5,
      "distance_percent": 0.95,
      "atr": 0.47,
      "atr_percent": 2.15,
      "last_volume": 221282,
      "avg_volume_14d": 354428,
      "golden_cross": false,
      "death_cross": false
    },
    {
      "symbol": "OSK",
      "last_close": 126.23,
      "sma150": 125.04,
      "distance_percent": 0.96,
      "atr": 3.94,
      "atr_percent": 3.05,
      "last_volume": 446820,
      "avg_volume_14d": 659150,
      "golden_cross": false,
      "death_cross": false
    },
    {
      "symbol": "KRC",
      "last_close": 38.95,
      "sma150": 38.58,
      "distance_percent": 0.97,
      "atr": 0.99,
      "atr_percent": 2.42,
      "last_volume": 821853,
      "avg_volume_14d": 1278007,
      "golden_cross": false,
      "death_cross": false
    },
    {
      "symbol": "ELC",
      "last_close": 20.72,
      "sma150": 20.52,
      "distance_percent": 0.97,
      "atr": 0.12,
      "atr_percent": 0.58,
      "last_volume": 23712,
      "avg_volume_14d": 33935,
      "golden_cross": false,
      "death_cross": false
    },
    {
      "symbol": "BIPH",
      "last_close": 16.83,
      "sma150": 16.66,
      "distance_percent": 1.05,
      "atr": 0.27,
      "atr_percent": 1.62,
      "last_volume": 6332,
      "avg_volume_14d": 11685,
      "golden_cross": false,
      "death_cross": false
    },
    {
      "symbol": "PMTU",
      "last_close": 25.41,
      "sma150": 25.13,
      "distance_percent": 1.11,
      "atr": 0.09,
      "atr_percent": 0.33,
      "last_volume": 2791,
      "avg_volume_14d": 2928,
      "golden_cross": false,
      "death_cross": false
    },
    {
      "symbol": "RWTO",
      "last_close": 24.82,
      "sma150": 24.54,
      "distance_percent": 1.13,
      "atr": 0.28,
      "atr_percent": 1.14,
      "last_volume": 12647,
      "avg_volume_14d": 5707,
      "golden_cross": false,
      "death_cross": false
    },
    {
      "symbol": "GPN",
      "last_close": 82.22,
      "sma150": 81.3,
      "distance_percent": 1.13,
      "atr": 2.02,
      "atr_percent": 2.53,
      "last_volume": 1212427,
      "avg_volume_14d": 2459542,
      "golden_cross": false,
      "death_cross": false
    },
    {
      "symbol": "APOS",
      "last_close": 26.0,
      "sma150": 25.7,
      "distance_percent": 1.16,
      "atr": 0.12,
      "atr_percent": 0.47,
      "last_volume": 32757,
      "avg_volume_14d": 65985,
      "golden_cross": false,
      "death_cross": false
    },
    {
      "symbol": "MAIN",
      "last_close": 60.53,
      "sma150": 59.82,
      "distance_percent": 1.18,
      "atr": 1.13,
      "atr_percent": 1.86,
      "last_volume": 359234,
      "avg_volume_14d": 451321,
      "golden_cross": false,
      "death_cross": false
    },
    {
      "symbol": "APTV",
      "last_close": 76.75,
      "sma150": 75.79,
      "distance_percent": 1.27,
      "atr": 1.7,
      "atr_percent": 2.2,
      "last_volume": 1550639,
      "avg_volume_14d": 1889271,
      "golden_cross": false,
      "death_cross": false
    },
    {
      "symbol": "CMSD",
      "last_close": 23.28,
      "sma150": 22.98,
      "distance_percent": 1.31,
      "atr": 0.2,
      "atr_percent": 0.86,
      "last_volume": 61596,
      "avg_volume_14d": 47142,
      "golden_cross": false,
      "death_cross": false
    },
    {
      "symbol": "SREA",
      "last_close": 22.23,
      "sma150": 21.94,
      "distance_percent": 1.31,
      "atr": 0.26,
      "atr_percent": 1.16,
      "last_volume": 39830,
      "avg_volume_14d": 69535,
      "golden_cross": false,
      "death_cross": false
    },
    {
      "symbol": "AQNB",
      "last_close": 25.6,
      "sma150": 25.27,
      "distance_percent": 1.31,
      "atr": 0.11,
      "atr_percent": 0.42,
      "last_volume": 19914,
      "avg_volume_14d": 22371,
      "golden_cross": false,
      "death_cross": false
    },
    {
      "symbol": "TKC",
      "last_close": 5.96,
      "sma150": 5.88,
      "distance_percent": 1.33,
      "atr": 0.07,
      "atr_percent": 1.12,
      "last_volume": 481728,
      "avg_volume_14d": 840492,
      "golden_cross": false,
      "death_cross": false
    },
    {
      "symbol": "O",
      "last_close": 57.76,
      "sma150": 56.97,
      "distance_percent": 1.39,
      "atr": 0.74,
      "atr_percent": 1.29,
      "last_volume": 4330624,
      "avg_volume_14d": 5783735,
      "golden_cross": false,
      "death_cross": false
    },
    {
      "symbol": "CNP",
      "last_close": 38.31,
      "sma150": 37.78,
      "distance_percent": 1.41,
      "atr": 0.54,
      "atr_percent": 1.41,
      "last_volume": 3888501,
      "avg_volume_14d": 4361471,
      "golden_cross": false,
      "death_cross": false
    },
    {
      "symbol": "CMSC",
      "last_close": 23.26,
      "sma150": 22.93,
      "distance_percent": 1.42,
      "atr": 0.17,
      "atr_percent": 0.71,
      "last_volume": 19912,
      "avg_volume_14d": 38228,
      "golden_cross": false,
      "death_cross": false
    },
    {
      "symbol": "WSM",
      "last_close": 185.69,
      "sma150": 183.01,
      "distance_percent": 1.46,
      "atr": 5.18,
      "atr_percent": 2.84,
      "last_volume": 756952,
      "avg_volume_14d": 1175271,
      "golden_cross": false,
      "death_cross": false
    },
    {
      "symbol": "HUM",
      "last_close": 260.28,
      "sma150": 256.52,
      "distance_percent": 1.47,
      "atr": 9.18,
      "atr_percent": 3.58,
      "last_volume": 823613,
      "avg_volume_14d": 1682257,
      "golden_cross": false,
      "death_cross": false
    },
    {
      "symbol": "DINO",
      "last_close": 47.44,
      "sma150": 46.75,
      "distance_percent": 1.47,
      "atr": 1.39,
      "atr_percent": 2.77,
      "last_volume": 2652782,
      "avg_volume_14d": 3021400,
      "golden_cross": false,
      "death_cross": false
    },
    {
      "symbol": "ABG",
      "last_close": 242.34,
      "sma150": 238.8,
      "distance_percent": 1.48,
      "atr": 7.34,
      "atr_percent": 3.07,
      "last_volume": 128094,
      "avg_volume_14d": 166357,
      "golden_cross": false,
      "death_cross": false
    },
    {
      "symbol": "BURL",
      "last_close": 268.18,
      "sma150": 264.17,
      "distance_percent": 1.52,
      "atr": 9.73,
      "atr_percent": 3.73,
      "last_volume": 623060,
      "avg_volume_14d": 1160478,
      "golden_cross": false,
      "death_cross": false
    },
    {
      "symbol": "TDS",
      "last_close": 38.29,
      "sma150": 37.72,
      "distance_percent": 1.52,
      "atr": 0.81,
      "atr_percent": 2.09,
      "last_volume": 849402,
      "avg_volume_14d": 979385,
      "golden_cross": false,
      "death_cross": false
    },
    {
      "symbol": "HUBB",
      "last_close": 429.68,
      "sma150": 422.96,
      "distance_percent": 1.59,
      "atr": 11.22,
      "atr_percent": 2.55,
      "last_volume": 481274,
      "avg_volume_14d": 458211,
      "golden_cross": false,
      "death_cross": false
    },
    {
      "symbol": "CPK",
      "last_close": 128.42,
      "sma150": 126.32,
      "distance_percent": 1.66,
      "atr": 2.82,
      "atr_percent": 2.17,
      "last_volume": 97895,
      "avg_volume_14d": 132485,
      "golden_cross": false,
      "death_cross": false
    },
    {
      "symbol": "BB",
      "last_close": 4.26,
      "sma150": 4.19,
      "distance_percent": 1.66,
      "atr": 0.14,
      "atr_percent": 3.17,
      "last_volume": 14482791,
      "avg_volume_14d": 5865642,
      "golden_cross": false,
      "death_cross": false
    },
    {
      "symbol": "UE",
      "last_close": 19.64,
      "sma150": 19.32,
      "distance_percent": 1.67,
      "atr": 0.31,
      "atr_percent": 1.63,
      "last_volume": 693788,
      "avg_volume_14d": 791192,
      "golden_cross": false,
      "death_cross": false
    },
    {
      "symbol": "MCO",
      "last_close": 499.02,
      "sma150": 490.8,
      "distance_percent": 1.67,
      "atr": 7.91,
      "atr_percent": 1.62,
      "last_volume": 681323,
      "avg_volume_14d": 787785,
      "golden_cross": false,
      "death_cross": false
    },
    {
      "symbol": "ITUB",
      "last_close": 7.04,
      "sma150": 6.92,
      "distance_percent": 1.74,
      "atr": 0.17,
      "atr_percent": 2.23,
      "last_volume": 28309357,
      "avg_volume_14d": 24466114,
      "golden_cross": false,
      "death_cross": false
    },
    {
      "symbol": "CFR",
      "last_close": 128.37,
      "sma150": 126.13,
      "distance_percent": 1.77,
      "atr": 2.52,
      "atr_percent": 1.98,
      "last_volume": 304136,
      "avg_volume_14d": 437614,
      "golden_cross": true,
      "death_cross": false
    },
    {
      "symbol": "LNT",
      "last_close": 65.48,
      "sma150": 64.32,
      "distance_percent": 1.8,
      "atr": 0.89,
      "atr_percent": 1.35,
      "last_volume": 2097045,
      "avg_volume_14d": 1835042,
      "golden_cross": false,
      "death_cross": false
    },
    {
      "symbol": "AIT",
      "last_close": 256.73,
      "sma150": 252.19,
      "distance_percent": 1.8,
      "atr": 5.39,
      "atr_percent": 2.08,
      "last_volume": 219170,
      "avg_volume_14d": 271492,
      "golden_cross": false,
      "death_cross": false
    },
    {
      "symbol": "DUKB",
      "last_close": 24.79,
      "sma150": 24.34,
      "distance_percent": 1.83,
      "atr": 0.16,
      "atr_percent": 0.66,
      "last_volume": 26686,
      "avg_volume_14d": 35421,
      "golden_cross": false,
      "death_cross": false
    },
    {
      "symbol": "AWI",
      "last_close": 184.6,
      "sma150": 181.25,
      "distance_percent": 1.85,
      "atr": 3.32,
      "atr_percent": 1.79,
      "last_volume": 239132,
      "avg_volume_14d": 296928,
      "golden_cross": false,
      "death_cross": false
    },
    {
      "symbol": "NAN",
      "last_close": 11.34,
      "sma150": 11.13,
      "distance_percent": 1.86,
      "atr": 0.09,
      "atr_percent": 0.77,
      "last_volume": 84469,
      "avg_volume_14d": 78700,
      "golden_cross": false,
      "death_cross": false
    },
    {
      "symbol": "PAGS",
      "last_close": 9.34,
      "sma150": 9.17,
      "distance_percent": 1.86,
      "atr": 0.44,
      "atr_percent": 4.31,
      "last_volume": 3121838,
      "avg_volume_14d": 4491535,
      "golden_cross": false,
      "death_cross": false
    },
    {
      "symbol": "BEN",
      "last_close": 23.67,
      "sma150": 23.24,
      "distance_percent": 1.87,
      "atr": 0.43,
      "atr_percent": 1.86,
      "last_volume": 2597606,
      "avg_volume_14d": 3367742,
      "golden_cross": false,
      "death_cross": false
    },
    {
      "symbol": "EC",
      "last_close": 9.35,
      "sma150": 9.17,
      "distance_percent": 1.91,
      "atr": 0.19,
      "atr_percent": 1.9,
      "last_volume": 1729574,
      "avg_volume_14d": 1913985,
      "golden_cross": false,
      "death_cross": false
    },
    {
      "symbol": "BN",
      "last_close": 44.52,
      "sma150": 43.67,
      "distance_percent": 1.95,
      "atr": 0.93,
      "atr_percent": 2.01,
      "last_volume": 3390599,
      "avg_volume_14d": 3787685,
      "golden_cross": false,
      "death_cross": false
    },
    {
      "symbol": "CURB",
      "last_close": 23.21,
      "sma150": 22.77,
      "distance_percent": 1.95,
      "atr": 0.7,
      "atr_percent": 3.01,
      "last_volume": 578485,
      "avg_volume_14d": 989635,
      "golden_cross": false,
      "death_cross": false
    },
    {
      "symbol": "RCB",
      "last_close": 24.5,
      "sma150": 24.02,
      "distance_percent": 1.99,
      "atr": 0.09,
      "atr_percent": 0.37,
      "last_volume": 5962,
      "avg_volume_14d": 3192,
      "golden_cross": false,
      "death_cross": false
    },
    {
      "symbol": "NOC",
      "last_close": 564.19,
      "sma150": 552.48,
      "distance_percent": 2.12,
      "atr": 10.17,
      "atr_percent": 1.82,
      "last_volume": 616805,
      "avg_volume_14d": 643328,
      "golden_cross": false,
      "death_cross": false
    },
    {
      "symbol": "BWXT",
      "last_close": 168.12,
      "sma150": 164.59,
      "distance_percent": 2.15,
      "atr": 5.82,
      "atr_percent": 3.3,
      "last_volume": 920554,
      "avg_volume_14d": 1012821,
      "golden_cross": false,
      "death_cross": false
    },
    {
      "symbol": "BNT",
      "last_close": 44.59,
      "sma150": 43.65,
      "distance_percent": 2.15,
      "atr": 0.78,
      "atr_percent": 1.69,
      "last_volume": 9919,
      "avg_volume_14d": 21757,
      "golden_cross": false,
      "death_cross": false
    },
    {
      "symbol": "MIR",
      "last_close": 22.98,
      "sma150": 22.49,
      "distance_percent": 2.19,
      "atr": 1.03,
      "atr_percent": 4.13,
      "last_volume": 1836289,
      "avg_volume_14d": 2804907,
      "golden_cross": false,
      "death_cross": false
    },
    {
      "symbol": "ITT",
      "last_close": 172.08,
      "sma150": 168.36,
      "distance_percent": 2.21,
      "atr": 5.12,
      "atr_percent": 2.9,
      "last_volume": 567490,
      "avg_volume_14d": 1333128,
      "golden_cross": false,
      "death_cross": false
    },
    {
      "symbol": "UI",
      "last_close": 542.54,
      "sma150": 530.6,
      "distance_percent": 2.25,
      "atr": 21.17,
      "atr_percent": 3.72,
      "last_volume": 72623,
      "avg_volume_14d": 101621,
      "golden_cross": false,
      "death_cross": false
    },
    {
      "symbol": "CEG",
      "last_close": 340.97,
      "sma150": 333.42,
      "distance_percent": 2.26,
      "atr": 15.82,
      "atr_percent": 4.39,
      "last_volume": 4540533,
      "avg_volume_14d": 2062685,
      "golden_cross": false,
      "death_cross": false
    },
    {
      "symbol": "HCXY",
      "last_close": 25.37,
      "sma150": 24.81,
      "distance_percent": 2.27,
      "atr": 0.12,
      "atr_percent": 0.46,
      "last_volume": 1833,
      "avg_volume_14d": 1021,
      "golden_cross": false,
      "death_cross": false
    },
    {
      "symbol": "PKX",
      "last_close": 52.88,
      "sma150": 51.69,
      "distance_percent": 2.3,
      "atr": 0.82,
      "atr_percent": 1.54,
      "last_volume": 112273,
      "avg_volume_14d": 137692,
      "golden_cross": false,
      "death_cross": false
    },
    {
      "symbol": "RWTN",
      "last_close": 24.59,
      "sma150": 24.04,
      "distance_percent": 2.3,
      "atr": 0.21,
      "atr_percent": 0.86,
      "last_volume": 33043,
      "avg_volume_14d": 6985,
      "golden_cross": false,
      "death_cross": false
    },
    {
      "symbol": "IDA",
      "last_close": 126.46,
      "sma150": 123.61,
      "distance_percent": 2.31,
      "atr": 2.15,
      "atr_percent": 1.69,
      "last_volume": 271492,
      "avg_volume_14d": 434092,
      "golden_cross": false,
      "death_cross": false
    },
    {
      "symbol": "RCC",
      "last_close": 24.94,
      "sma150": 24.36,
      "distance_percent": 2.39,
      "atr": 0.08,
      "atr_percent": 0.32,
      "last_volume": 7417,
      "avg_volume_14d": 4385,
      "golden_cross": false,
      "death_cross": false
    },
    {
      "symbol": "TDW",
      "last_close": 53.18,
      "sma150": 51.93,
      "distance_percent": 2.4,
      "atr": 2.31,
      "atr_percent": 4.1,
      "last_volume": 655153,
      "avg_volume_14d": 666207,
      "golden_cross": false,
      "death_cross": false
    },
    {
      "symbol": "GBCI",
      "last_close": 45.13,
      "sma150": 44.06,
      "distance_percent": 2.44,
      "atr": 1.01,
      "atr_percent": 2.34,
      "last_volume": 749277,
      "avg_volume_14d": 743828,
      "golden_cross": false,
      "death_cross": false
    },
    {
      "symbol": "STNG",
      "last_close": 51.83,
      "sma150": 50.6,
      "distance_percent": 2.44,
      "atr": 1.46,
      "atr_percent": 2.68,
      "last_volume": 739628,
      "avg_volume_14d": 1276828,
      "golden_cross": false,
      "death_cross": false
    },
    {
      "symbol": "CPA",
      "last_close": 118.35,
      "sma150": 115.52,
      "distance_percent": 2.45,
      "atr": 2.68,
      "atr_percent": 2.25,
      "last_volume": 233022,
      "avg_volume_14d": 272485,
      "golden_cross": false,
      "death_cross": false
    },
    {
      "symbol": "MFAO",
      "last_close": 25.21,
      "sma150": 24.6,
      "distance_percent": 2.49,
      "atr": 0.11,
      "atr_percent": 0.43,
      "last_volume": 8416,
      "avg_volume_14d": 17021,
      "golden_cross": false,
      "death_cross": false
    },
    {
      "symbol": "TROW",
      "last_close": 103.9,
      "sma150": 101.34,
      "distance_percent": 2.53,
      "atr": 1.99,
      "atr_percent": 1.91,
      "last_volume": 2086063,
      "avg_volume_14d": 1960671,
      "golden_cross": false,
      "death_cross": false
    },
    {
      "symbol": "CUK",
      "last_close": 26.05,
      "sma150": 25.4,
      "distance_percent": 2.54,
      "atr": 0.63,
      "atr_percent": 2.57,
      "last_volume": 1566107,
      "avg_volume_14d": 1806914,
      "golden_cross": false,
      "death_cross": false
    },
    {
      "symbol": "FG",
      "last_close": 32.83,
      "sma150": 32.01,
      "distance_percent": 2.56,
      "atr": 0.96,
      "atr_percent": 2.86,
      "last_volume": 374774,
      "avg_volume_14d": 180914,
      "golden_cross": false,
      "death_cross": false
    },
    {
      "symbol": "NE",
      "last_close": 28.52,
      "sma150": 27.81,
      "distance_percent": 2.57,
      "atr": 1.2,
      "atr_percent": 3.87,
      "last_volume": 1488979,
      "avg_volume_14d": 1829350,
      "golden_cross": false,
      "death_cross": false
    },
    {
      "symbol": "DHI",
      "last_close": 152.0,
      "sma150": 148.19,
      "distance_percent": 2.57,
      "atr": 3.98,
      "atr_percent": 2.54,
      "last_volume": 3449356,
      "avg_volume_14d": 2878435,
      "golden_cross": false,
      "death_cross": false
    },
    {
      "symbol": "BNL",
      "last_close": 17.51,
      "sma150": 17.06,
      "distance_percent": 2.61,
      "atr": 0.29,
      "atr_percent": 1.64,
      "last_volume": 1596206,
      "avg_volume_14d": 2131828,
      "golden_cross": false,
      "death_cross": false
    },
    {
      "symbol": "PK",
      "last_close": 10.95,
      "sma150": 10.66,
      "distance_percent": 2.69,
      "atr": 0.29,
      "atr_percent": 2.7,
      "last_volume": 1701628,
      "avg_volume_14d": 3729535,
      "golden_cross": false,
      "death_cross": false
    },
    {
      "symbol": "HOMB",
      "last_close": 28.88,
      "sma150": 28.12,
      "distance_percent": 2.7,
      "atr": 0.51,
      "atr_percent": 1.79,
      "last_volume": 1116745,
      "avg_volume_14d": 1246871,
      "golden_cross": false,
      "death_cross": false
    },
    {
      "symbol": "CIMN",
      "last_close": 25.22,
      "sma150": 24.55,
      "distance_percent": 2.73,
      "atr": 0.12,
      "atr_percent": 0.48,
      "last_volume": 1404,
      "avg_volume_14d": 4985,
      "golden_cross": false,
      "death_cross": false
    },
    {
      "symbol": "KO",
      "last_close": 70.67,
      "sma150": 68.79,
      "distance_percent": 2.73,
      "atr": 1.0,
      "atr_percent": 1.41,
      "last_volume": 10371144,
      "avg_volume_14d": 17167235,
      "golden_cross": false,
      "death_cross": false
    },
    {
      "symbol": "EXE",
      "last_close": 109.54,
      "sma150": 106.57,
      "distance_percent": 2.78,
      "atr": 3.44,
      "atr_percent": 2.94,
      "last_volume": 3610441,
      "avg_volume_14d": 3224471,
      "golden_cross": false,
      "death_cross": false
    },
    {
      "symbol": "ALV",
      "last_close": 119.61,
      "sma150": 116.35,
      "distance_percent": 2.8,
      "atr": 2.28,
      "atr_percent": 1.91,
      "last_volume": 413396,
      "avg_volume_14d": 537614,
      "golden_cross": false,
      "death_cross": false
    },
    {
      "symbol": "LHX",
      "last_close": 278.72,
      "sma150": 271.07,
      "distance_percent": 2.82,
      "atr": 5.97,
      "atr_percent": 2.12,
      "last_volume": 907974,
      "avg_volume_14d": 1031035,
      "golden_cross": false,
      "death_cross": false
    },
    {
      "symbol": "GJS",
      "last_close": 23.26,
      "sma150": 22.62,
      "distance_percent": 2.83,
      "atr": 0.05,
      "atr_percent": 0.21,
      "last_volume": 1492,
      "avg_volume_14d": 1357,
      "golden_cross": false,
      "death_cross": false
    },
    {
      "symbol": "CDP",
      "last_close": 29.18,
      "sma150": 28.38,
      "distance_percent": 2.83,
      "atr": 0.56,
      "atr_percent": 1.88,
      "last_volume": 429526,
      "avg_volume_14d": 798264,
      "golden_cross": false,
      "death_cross": false
    },
    {
      "symbol": "MFAN",
      "last_close": 25.16,
      "sma150": 24.47,
      "distance_percent": 2.83,
      "atr": 0.11,
      "atr_percent": 0.45,
      "last_volume": 14116,
      "avg_volume_14d": 26057,
      "golden_cross": false,
      "death_cross": false
    },
    {
      "symbol": "CLH",
      "last_close": 237.82,
      "sma150": 231.26,
      "distance_percent": 2.84,
      "atr": 4.79,
      "atr_percent": 2.02,
      "last_volume": 166453,
      "avg_volume_14d": 530764,
      "golden_cross": false,
      "death_cross": false
    },
    {
      "symbol": "DAR",
      "last_close": 34.6,
      "sma150": 33.64,
      "distance_percent": 2.85,
      "atr": 1.13,
      "atr_percent": 3.14,
      "last_volume": 1603299,
      "avg_volume_14d": 1913092,
      "golden_cross": false,
      "death_cross": false
    },
    {
      "symbol": "BNH",
      "last_close": 16.3,
      "sma150": 15.85,
      "distance_percent": 2.85,
      "atr": 0.21,
      "atr_percent": 1.31,
      "last_volume": 22261,
      "avg_volume_14d": 18157,
      "golden_cross": false,
      "death_cross": false
    },
    {
      "symbol": "TECH",
      "last_close": 56.99,
      "sma150": 55.41,
      "distance_percent": 2.86,
      "atr": 1.97,
      "atr_percent": 3.23,
      "last_volume": 1505274,
      "avg_volume_14d": 1777735,
      "golden_cross": false,
      "death_cross": false
    },
    {
      "symbol": "SNX",
      "last_close": 148.98,
      "sma150": 144.8,
      "distance_percent": 2.89,
      "atr": 3.26,
      "atr_percent": 2.12,
      "last_volume": 526060,
      "avg_volume_14d": 670557,
      "golden_cross": false,
      "death_cross": false
    },
    {
      "symbol": "ECCF",
      "last_close": 25.24,
      "sma150": 24.52,
      "distance_percent": 2.92,
      "atr": 0.14,
      "atr_percent": 0.55,
      "last_volume": 712,
      "avg_volume_14d": 4714,
      "golden_cross": false,
      "death_cross": false
    },
    {
      "symbol": "WTW",
      "last_close": 329.84,
      "sma150": 320.46,
      "distance_percent": 2.93,
      "atr": 5.93,
      "atr_percent": 1.84,
      "last_volume": 617583,
      "avg_volume_14d": 686700,
      "golden_cross": false,
      "death_cross": false
    },
    {
      "symbol": "LMT",
      "last_close": 474.79,
      "sma150": 461.26,
      "distance_percent": 2.93,
      "atr": 9.49,
      "atr_percent": 2.05,
      "last_volume": 1658027,
      "avg_volume_14d": 1379850,
      "golden_cross": false,
      "death_cross": false
    },
    {
      "symbol": "UGP",
      "last_close": 3.65,
      "sma150": 3.55,
      "distance_percent": 2.95,
      "atr": 0.11,
      "atr_percent": 2.88,
      "last_volume": 1612298,
      "avg_volume_14d": 2135821,
      "golden_cross": false,
      "death_cross": false
    },
    {
      "symbol": "RNST",
      "last_close": 37.32,
      "sma150": 36.25,
      "distance_percent": 2.96,
      "atr": 0.69,
      "atr_percent": 1.91,
      "last_volume": 442146,
      "avg_volume_14d": 570435,
      "golden_cross": false,
      "death_cross": false
    },
    {
      "symbol": "SOBO",
      "last_close": 27.64,
      "sma150": 26.83,
      "distance_percent": 3.02,
      "atr": 0.5,
      "atr_percent": 1.81,
      "last_volume": 379416,
      "avg_volume_14d": 704821,
      "golden_cross": false,
      "death_cross": false
    },
    {
      "symbol": "HWM",
      "last_close": 191.19,
      "sma150": 185.56,
      "distance_percent": 3.03,
      "atr": 5.35,
      "atr_percent": 2.74,
      "last_volume": 1922479,
      "avg_volume_14d": 2178707,
      "golden_cross": false,
      "death_cross": false
    },
    {
      "symbol": "CMBT",
      "last_close": 9.69,
      "sma150": 9.4,
      "distance_percent": 3.07,
      "atr": 0.28,
      "atr_percent": 2.66,
      "last_volume": 1518827,
      "avg_volume_14d": 2046264,
      "golden_cross": false,
      "death_cross": false
    },
    {
      "symbol": "BKR",
      "last_close": 45.29,
      "sma150": 43.94,
      "distance_percent": 3.08,
      "atr": 1.3,
      "atr_percent": 2.7,
      "last_volume": 8625146,
      "avg_volume_14d": 6742192,
      "golden_cross": false,
      "death_cross": false
    },
    {
      "symbol": "EVRG",
      "last_close": 73.59,
      "sma150": 71.35,
      "distance_percent": 3.13,
      "atr": 1.05,
      "atr_percent": 1.41,
      "last_volume": 1799199,
      "avg_volume_14d": 1868428,
      "golden_cross": false,
      "death_cross": false
    },
    {
      "symbol": "HR",
      "last_close": 17.11,
      "sma150": 16.59,
      "distance_percent": 3.16,
      "atr": 0.31,
      "atr_percent": 1.8,
      "last_volume": 2771102,
      "avg_volume_14d": 2858414,
      "golden_cross": false,
      "death_cross": false
    },
    {
      "symbol": "PHM",
      "last_close": 122.8,
      "sma150": 119.04,
      "distance_percent": 3.16,
      "atr": 2.96,
      "atr_percent": 2.34,
      "last_volume": 1604772,
      "avg_volume_14d": 1482200,
      "golden_cross": false,
      "death_cross": false
    },
    {
      "symbol": "VIST",
      "last_close": 45.9,
      "sma150": 44.47,
      "distance_percent": 3.21,
      "atr": 1.93,
      "atr_percent": 3.86,
      "last_volume": 814181,
      "avg_volume_14d": 744407,
      "golden_cross": true,
      "death_cross": false
    },
    {
      "symbol": "STE",
      "last_close": 251.67,
      "sma150": 243.77,
      "distance_percent": 3.24,
      "atr": 4.88,
      "atr_percent": 1.89,
      "last_volume": 312740,
      "avg_volume_14d": 588871,
      "golden_cross": false,
      "death_cross": false
    },
    {
      "symbol": "ESI",
      "last_close": 25.39,
      "sma150": 24.59,
      "distance_percent": 3.25,
      "atr": 0.8,
      "atr_percent": 3.04,
      "last_volume": 1125276,
      "avg_volume_14d": 2270735,
      "golden_cross": false,
      "death_cross": false
    },
    {
      "symbol": "ADM",
      "last_close": 58.56,
      "sma150": 56.71,
      "distance_percent": 3.26,
      "atr": 1.29,
      "atr_percent": 2.18,
      "last_volume": 2514175,
      "avg_volume_14d": 2463635,
      "golden_cross": false,
      "death_cross": false
    },
    {
      "symbol": "GFF",
      "last_close": 76.67,
      "sma150": 74.25,
      "distance_percent": 3.26,
      "atr": 1.65,
      "atr_percent": 2.2,
      "last_volume": 166522,
      "avg_volume_14d": 298135,
      "golden_cross": false,
      "death_cross": false
    },
    {
      "symbol": "FE",
      "last_close": 44.5,
      "sma150": 43.09,
      "distance_percent": 3.26,
      "atr": 0.7,
      "atr_percent": 1.55,
      "last_volume": 3518831,
      "avg_volume_14d": 4473142,
      "golden_cross": false,
      "death_cross": false
    },
    {
      "symbol": "DKL",
      "last_close": 44.22,
      "sma150": 42.82,
      "distance_percent": 3.27,
      "atr": 1.07,
      "atr_percent": 2.35,
      "last_volume": 20751,
      "avg_volume_14d": 43242,
      "golden_cross": false,
      "death_cross": false
    },
    {
      "symbol": "PWR",
      "last_close": 414.25,
      "sma150": 400.8,
      "distance_percent": 3.36,
      "atr": 15.16,
      "atr_percent": 3.35,
      "last_volume": 1555106,
      "avg_volume_14d": 921692,
      "golden_cross": false,
      "death_cross": false
    },
    {
      "symbol": "PFE",
      "last_close": 25.04,
      "sma150": 24.22,
      "distance_percent": 3.4,
      "atr": 0.59,
      "atr_percent": 2.31,
      "last_volume": 51976496,
      "avg_volume_14d": 48834785,
      "golden_cross": false,
      "death_cross": false
    },
    {
      "symbol": "OGS",
      "last_close": 78.62,
      "sma150": 75.99,
      "distance_percent": 3.46,
      "atr": 1.36,
      "atr_percent": 1.73,
      "last_volume": 316484,
      "avg_volume_14d": 455392,
      "golden_cross": false,
      "death_cross": false
    },
    {
      "symbol": "ETR",
      "last_close": 91.83,
      "sma150": 88.75,
      "distance_percent": 3.47,
      "atr": 1.64,
      "atr_percent": 1.75,
      "last_volume": 2498789,
      "avg_volume_14d": 2771164,
      "golden_cross": false,
      "death_cross": false
    },
    {
      "symbol": "D",
      "last_close": 60.11,
      "sma150": 58.07,
      "distance_percent": 3.5,
      "atr": 1.0,
      "atr_percent": 1.69,
      "last_volume": 6735838,
      "avg_volume_14d": 6154550,
      "golden_cross": false,
      "death_cross": false
    },
    {
      "symbol": "ENJ",
      "last_close": 21.6,
      "sma150": 20.87,
      "distance_percent": 3.52,
      "atr": 0.27,
      "atr_percent": 1.25,
      "last_volume": 4826,
      "avg_volume_14d": 2821,
      "golden_cross": false,
      "death_cross": false
    },
    {
      "symbol": "SWK",
      "last_close": 71.92,
      "sma150": 69.47,
      "distance_percent": 3.53,
      "atr": 2.05,
      "atr_percent": 2.81,
      "last_volume": 1576709,
      "avg_volume_14d": 1567414,
      "golden_cross": false,
      "death_cross": false
    },
    {
      "symbol": "EPD",
      "last_close": 32.02,
      "sma150": 30.93,
      "distance_percent": 3.54,
      "atr": 0.39,
      "atr_percent": 1.2,
      "last_volume": 3594099,
      "avg_volume_14d": 3300785,
      "golden_cross": false,
      "death_cross": false
    },
    {
      "symbol": "STAG",
      "last_close": 37.49,
      "sma150": 36.21,
      "distance_percent": 3.55,
      "atr": 0.57,
      "atr_percent": 1.48,
      "last_volume": 2001700,
      "avg_volume_14d": 1247814,
      "golden_cross": false,
      "death_cross": false
    },
    {
      "symbol": "KB",
      "last_close": 84.21,
      "sma150": 81.31,
      "distance_percent": 3.57,
      "atr": 1.1,
      "atr_percent": 1.27,
      "last_volume": 84935,
      "avg_volume_14d": 121878,
      "golden_cross": false,
      "death_cross": false
    },
    {
      "symbol": "NXPI",
      "last_close": 223.23,
      "sma150": 215.47,
      "distance_percent": 3.6,
      "atr": 6.96,
      "atr_percent": 3.13,
      "last_volume": 2682351,
      "avg_volume_14d": 3056207,
      "golden_cross": false,
      "death_cross": false
    },
    {
      "symbol": "MHO",
      "last_close": 133.5,
      "sma150": 128.85,
      "distance_percent": 3.61,
      "atr": 3.69,
      "atr_percent": 2.74,
      "last_volume": 144123,
      "avg_volume_14d": 184628,
      "golden_cross": false,
      "death_cross": false
    },
    {
      "symbol": "PSX",
      "last_close": 131.99,
      "sma150": 127.4,
      "distance_percent": 3.61,
      "atr": 3.69,
      "atr_percent": 2.66,
      "last_volume": 4554185,
      "avg_volume_14d": 2260671,
      "golden_cross": false,
      "death_cross": false
    },
    {
      "symbol": "PCOR",
      "last_close": 73.41,
      "sma150": 70.85,
      "distance_percent": 3.62,
      "atr": 2.22,
      "atr_percent": 2.94,
      "last_volume": 881631,
      "avg_volume_14d": 1209028,
      "golden_cross": false,
      "death_cross": false
    },
    {
      "symbol": "ATO",
      "last_close": 169.17,
      "sma150": 163.25,
      "distance_percent": 3.63,
      "atr": 2.83,
      "atr_percent": 1.67,
      "last_volume": 824620,
      "avg_volume_14d": 1027564,
      "golden_cross": false,
      "death_cross": false
    },
    {
      "symbol": "LDOS",
      "last_close": 181.36,
      "sma150": 174.99,
      "distance_percent": 3.64,
      "atr": 4.24,
      "atr_percent": 2.26,
      "last_volume": 541782,
      "avg_volume_14d": 795742,
      "golden_cross": false,
      "death_cross": false
    },
    {
      "symbol": "VRT",
      "last_close": 149.83,
      "sma150": 144.44,
      "distance_percent": 3.73,
      "atr": 8.95,
      "atr_percent": 5.12,
      "last_volume": 11848812,
      "avg_volume_14d": 6906335,
      "golden_cross": false,
      "death_cross": false
    },
    {
      "symbol": "ALE",
      "last_close": 67.9,
      "sma150": 65.45,
      "distance_percent": 3.74,
      "atr": 0.13,
      "atr_percent": 0.19,
      "last_volume": 4388747,
      "avg_volume_14d": 986350,
      "golden_cross": false,
      "death_cross": false
    },
    {
      "symbol": "HAYW",
      "last_close": 15.78,
      "sma150": 15.21,
      "distance_percent": 3.75,
      "atr": 0.33,
      "atr_percent": 2.03,
      "last_volume": 913882,
      "avg_volume_14d": 1345735,
      "golden_cross": false,
      "death_cross": false
    },
    {
      "symbol": "BIPJ",
      "last_close": 25.04,
      "sma150": 24.13,
      "distance_percent": 3.76,
      "atr": 0.21,
      "atr_percent": 0.84,
      "last_volume": 6767,
      "avg_volume_14d": 10442,
      "golden_cross": false,
      "death_cross": false
    },
    {
      "symbol": "WES",
      "last_close": 39.19,
      "sma150": 37.75,
      "distance_percent": 3.82,
      "atr": 0.71,
      "atr_percent": 1.8,
      "last_volume": 729584,
      "avg_volume_14d": 1456214,
      "golden_cross": false,
      "death_cross": false
    },
    {
      "symbol": "ALL",
      "last_close": 209.08,
      "sma150": 201.36,
      "distance_percent": 3.83,
      "atr": 3.59,
      "atr_percent": 1.74,
      "last_volume": 1363305,
      "avg_volume_14d": 1521178,
      "golden_cross": false,
      "death_cross": false
    },
    {
      "symbol": "GDV",
      "last_close": 27.06,
      "sma150": 26.06,
      "distance_percent": 3.85,
      "atr": 0.3,
      "atr_percent": 1.09,
      "last_volume": 59906,
      "avg_volume_14d": 96028,
      "golden_cross": false,
      "death_cross": false
    },
    {
      "symbol": "RVTY",
      "last_close": 96.77,
      "sma150": 93.14,
      "distance_percent": 3.9,
      "atr": 2.99,
      "atr_percent": 2.96,
      "last_volume": 1083851,
      "avg_volume_14d": 1220342,
      "golden_cross": false,
      "death_cross": false
    },
    {
      "symbol": "MTN",
      "last_close": 156.44,
      "sma150": 150.56,
      "distance_percent": 3.9,
      "atr": 4.65,
      "atr_percent": 3.15,
      "last_volume": 880663,
      "avg_volume_14d": 996857,
      "golden_cross": false,
      "death_cross": false
    },
    {
      "symbol": "CAE",
      "last_close": 28.64,
      "sma150": 27.56,
      "distance_percent": 3.91,
      "atr": 0.68,
      "atr_percent": 2.42,
      "last_volume": 321403,
      "avg_volume_14d": 624307,
      "golden_cross": false,
      "death_cross": false
    },
    {
      "symbol": "AVGO",
      "last_close": 326.02,
      "sma150": 313.65,
      "distance_percent": 3.94,
      "atr": 14.11,
      "atr_percent": 3.72,
      "last_volume": 64027793,
      "avg_volume_14d": 35799528,
      "golden_cross": false,
      "death_cross": false
    },
    {
      "symbol": "EMA",
      "last_close": 48.54,
      "sma150": 46.7,
      "distance_percent": 3.95,
      "atr": 0.61,
      "atr_percent": 1.27,
      "last_volume": 303492,
      "avg_volume_14d": 229521,
      "golden_cross": false,
      "death_cross": false
    },
    {
      "symbol": "TXNM",
      "last_close": 58.71,
      "sma150": 56.48,
      "distance_percent": 3.95,
      "atr": 0.28,
      "atr_percent": 0.48,
      "last_volume": 631218,
      "avg_volume_14d": 858300,
      "golden_cross": false,
      "death_cross": false
    },
    {
      "symbol": "SCHW",
      "last_close": 96.61,
      "sma150": 92.93,
      "distance_percent": 3.96,
      "atr": 1.88,
      "atr_percent": 1.98,
      "last_volume": 7788248,
      "avg_volume_14d": 8992878,
      "golden_cross": false,
      "death_cross": false
    },
    {
      "symbol": "K",
      "last_close": 83.44,
      "sma150": 80.26,
      "distance_percent": 3.97,
      "atr": 0.11,
      "atr_percent": 0.13,
      "last_volume": 0,
      "avg_volume_14d": 6000225,
      "golden_cross": false,
      "death_cross": false
    },
    {
      "symbol": "IVT",
      "last_close": 29.07,
      "sma150": 27.96,
      "distance_percent": 3.97,
      "atr": 0.46,
      "atr_percent": 1.61,
      "last_volume": 484610,
      "avg_volume_14d": 531935,
      "golden_cross": false,
      "death_cross": false
    },
    {
      "symbol": "BIP",
      "last_close": 34.1,
      "sma150": 32.8,
      "distance_percent": 3.97,
      "atr": 0.64,
      "atr_percent": 1.83,
      "last_volume": 685541,
      "avg_volume_14d": 765078,
      "golden_cross": false,
      "death_cross": false
    }
  ],
  "watch_list": [
    {
      "symbol": "EMR",
      "last_close": 131.64,
      "sma150": 131.67,
      "distance_percent": -0.02,
      "atr": 2.9,
      "atr_percent": 2.15,
      "last_volume": 3492137,
      "avg_volume_14d": 2145864,
      "golden_cross": false,
      "death_cross": false
    },
    {
      "symbol": "TRMB",
      "last_close": 78.89,
      "sma150": 78.93,
      "distance_percent": -0.05,
      "atr": 1.81,
      "atr_percent": 2.22,
      "last_volume": 1507436,
      "avg_volume_14d": 1124764,
      "golden_cross": false,
      "death_cross": false
    },
    {
      "symbol": "EME",
      "last_close": 596.47,
      "sma150": 597.27,
      "distance_percent": -0.13,
      "atr": 19.94,
      "atr_percent": 3.21,
      "last_volume": 463608,
      "avg_volume_14d": 349850,
      "golden_cross": false,
      "death_cross": false
    },
    {
      "symbol": "DTW",
      "last_close": 21.53,
      "sma150": 21.56,
      "distance_percent": -0.14,
      "atr": 0.29,
      "atr_percent": 1.35,
      "last_volume": 39649,
      "avg_volume_14d": 38700,
      "golden_cross": false,
      "death_cross": false
    },
    {
      "symbol": "RLX",
      "last_close": 2.33,
      "sma150": 2.33,
      "distance_percent": -0.15,
      "atr": 0.06,
      "atr_percent": 2.4,
      "last_volume": 1985429,
      "avg_volume_14d": 1766400,
      "golden_cross": false,
      "death_cross": false
    },
    {
      "symbol": "FGN",
      "last_close": 25.53,
      "sma150": 25.57,
      "distance_percent": -0.15,
      "atr": 0.27,
      "atr_percent": 1.04,
      "last_volume": 23217,
      "avg_volume_14d": 21971,
      "golden_cross": false,
      "death_cross": false
    },
    {
      "symbol": "ALLE",
      "last_close": 160.71,
      "sma150": 160.99,
      "distance_percent": -0.18,
      "atr": 3.45,
      "atr_percent": 2.13,
      "last_volume": 755881,
      "avg_volume_14d": 833607,
      "golden_cross": false,
      "death_cross": false
    },
    {
      "symbol": "SOJD",
      "last_close": 20.28,
      "sma150": 20.32,
      "distance_percent": -0.18,
      "atr": 0.17,
      "atr_percent": 0.83,
      "last_volume": 138331,
      "avg_volume_14d": 138992,
      "golden_cross": false,
      "death_cross": false
    },
    {
      "symbol": "USFD",
      "last_close": 77.11,
      "sma150": 77.26,
      "distance_percent": -0.2,
      "atr": 1.27,
      "atr_percent": 1.66,
      "last_volume": 1283074,
      "avg_volume_14d": 2023500,
      "golden_cross": false,
      "death_cross": false
    },
    {
      "symbol": "RYN",
      "last_close": 22.46,
      "sma150": 22.53,
      "distance_percent": -0.32,
      "atr": 0.53,
      "atr_percent": 2.43,
      "last_volume": 1968038,
      "avg_volume_14d": 1434250,
      "golden_cross": false,
      "death_cross": false
    },
    {
      "symbol": "ESE",
      "last_close": 199.57,
      "sma150": 200.32,
      "distance_percent": -0.37,
      "atr": 5.6,
      "atr_percent": 2.76,
      "last_volume": 174065,
      "avg_volume_14d": 243800,
      "golden_cross": false,
      "death_cross": false
    },
    {
      "symbol": "AOS",
      "last_close": 68.08,
      "sma150": 68.34,
      "distance_percent": -0.39,
      "atr": 1.35,
      "atr_percent": 2.0,
      "last_volume": 761958,
      "avg_volume_14d": 1402385,
      "golden_cross": false,
      "death_cross": false
    },
    {
      "symbol": "BKNG",
      "last_close": 5340.98,
      "sma150": 5361.69,
      "distance_percent": -0.39,
      "atr": 138.01,
      "atr_percent": 2.66,
      "last_volume": 170510,
      "avg_volume_14d": 281242,
      "golden_cross": false,
      "death_cross": false
    },
    {
      "symbol": "FERG",
      "last_close": 225.0,
      "sma150": 226.06,
      "distance_percent": -0.47,
      "atr": 5.32,
      "atr_percent": 2.23,
      "last_volume": 1667361,
      "avg_volume_14d": 1752164,
      "golden_cross": false,
      "death_cross": false
    },
    {
      "symbol": "SUI",
      "last_close": 124.13,
      "sma150": 124.74,
      "distance_percent": -0.49,
      "atr": 2.39,
      "atr_percent": 1.91,
      "last_volume": 543709,
      "avg_volume_14d": 758607,
      "golden_cross": false,
      "death_cross": false
    },
    {
      "symbol": "AGCO",
      "last_close": 106.36,
      "sma150": 106.91,
      "distance_percent": -0.52,
      "atr": 3.33,
      "atr_percent": 3.13,
      "last_volume": 696969,
      "avg_volume_14d": 816028,
      "golden_cross": false,
      "death_cross": false
    },
    {
      "symbol": "CIG",
      "last_close": 1.96,
      "sma150": 1.97,
      "distance_percent": -0.55,
      "atr": 0.05,
      "atr_percent": 2.21,
      "last_volume": 4872104,
      "avg_volume_14d": 3072285,
      "golden_cross": false,
      "death_cross": false
    },
    {
      "symbol": "TR",
      "last_close": 37.82,
      "sma150": 38.03,
      "distance_percent": -0.56,
      "atr": 0.76,
      "atr_percent": 2.02,
      "last_volume": 81943,
      "avg_volume_14d": 114835,
      "golden_cross": false,
      "death_cross": false
    },
    {
      "symbol": "AEE",
      "last_close": 98.53,
      "sma150": 99.1,
      "distance_percent": -0.58,
      "atr": 1.51,
      "atr_percent": 1.52,
      "last_volume": 1575623,
      "avg_volume_14d": 1897078,
      "golden_cross": false,
      "death_cross": false
    },
    {
      "symbol": "NVDA",
      "last_close": 170.94,
      "sma150": 171.94,
      "distance_percent": -0.58,
      "atr": 4.56,
      "atr_percent": 2.54,
      "last_volume": 219595489,
      "avg_volume_14d": 168862885,
      "golden_cross": false,
      "death_cross": false
    },
    {
      "symbol": "SOJC",
      "last_close": 21.77,
      "sma150": 21.9,
      "distance_percent": -0.59,
      "atr": 0.18,
      "atr_percent": 0.85,
      "last_volume": 27447,
      "avg_volume_14d": 38314,
      "golden_cross": false,
      "death_cross": false
    },
    {
      "symbol": "UNMA",
      "last_close": 23.15,
      "sma150": 23.29,
      "distance_percent": -0.59,
      "atr": 0.21,
      "atr_percent": 0.91,
      "last_volume": 43782,
      "avg_volume_14d": 32592,
      "golden_cross": false,
      "death_cross": false
    },
    {
      "symbol": "CR",
      "last_close": 183.83,
      "sma150": 185.04,
      "distance_percent": -0.65,
      "atr": 3.97,
      "atr_percent": 2.12,
      "last_volume": 147162,
      "avg_volume_14d": 317928,
      "golden_cross": false,
      "death_cross": false
    },
    {
      "symbol": "XYL",
      "last_close": 136.88,
      "sma150": 137.89,
      "distance_percent": -0.73,
      "atr": 2.24,
      "atr_percent": 1.62,
      "last_volume": 1020557,
      "avg_volume_14d": 1383542,
      "golden_cross": false,
      "death_cross": false
    },
    {
      "symbol": "PAG",
      "last_close": 167.85,
      "sma150": 169.09,
      "distance_percent": -0.73,
      "atr": 3.0,
      "atr_percent": 1.81,
      "last_volume": 210448,
      "avg_volume_14d": 218607,
      "golden_cross": false,
      "death_cross": false
    },
    {
      "symbol": "BXP",
      "last_close": 69.54,
      "sma150": 70.06,
      "distance_percent": -0.74,
      "atr": 1.55,
      "atr_percent": 2.2,
      "last_volume": 1305706,
      "avg_volume_14d": 1229150,
      "golden_cross": false,
      "death_cross": false
    },
    {
      "symbol": "DTG",
      "last_close": 17.22,
      "sma150": 17.35,
      "distance_percent": -0.75,
      "atr": 0.18,
      "atr_percent": 1.02,
      "last_volume": 54334,
      "avg_volume_14d": 51792,
      "golden_cross": false,
      "death_cross": false
    },
    {
      "symbol": "SMG",
      "last_close": 58.74,
      "sma150": 59.2,
      "distance_percent": -0.78,
      "atr": 1.75,
      "atr_percent": 3.13,
      "last_volume": 793798,
      "avg_volume_14d": 769050,
      "golden_cross": false,
      "death_cross": false
    },
    {
      "symbol": "GPC",
      "last_close": 128.06,
      "sma150": 129.08,
      "distance_percent": -0.79,
      "atr": 2.43,
      "atr_percent": 1.88,
      "last_volume": 824920,
      "avg_volume_14d": 1152800,
      "golden_cross": false,
      "death_cross": false
    },
    {
      "symbol": "EQT",
      "last_close": 54.36,
      "sma150": 54.8,
      "distance_percent": -0.81,
      "atr": 1.83,
      "atr_percent": 3.15,
      "last_volume": 7069549,
      "avg_volume_14d": 8425128,
      "golden_cross": false,
      "death_cross": false
    },
    {
      "symbol": "MOD",
      "last_close": 128.39,
      "sma150": 129.45,
      "distance_percent": -0.82,
      "atr": 10.78,
      "atr_percent": 7.03,
      "last_volume": 2581827,
      "avg_volume_14d": 1141664,
      "golden_cross": false,
      "death_cross": false
    },
    {
      "symbol": "GRBK",
      "last_close": 65.44,
      "sma150": 65.99,
      "distance_percent": -0.83,
      "atr": 1.65,
      "atr_percent": 2.5,
      "last_volume": 174258,
      "avg_volume_14d": 241328,
      "golden_cross": false,
      "death_cross": false
    },
    {
      "symbol": "BRX",
      "last_close": 25.95,
      "sma150": 26.17,
      "distance_percent": -0.84,
      "atr": 0.41,
      "atr_percent": 1.59,
      "last_volume": 1551501,
      "avg_volume_14d": 3180457,
      "golden_cross": false,
      "death_cross": false
    },
    {
      "symbol": "WMB",
      "last_close": 58.84,
      "sma150": 59.34,
      "distance_percent": -0.84,
      "atr": 1.34,
      "atr_percent": 2.21,
      "last_volume": 5419236,
      "avg_volume_14d": 6423050,
      "golden_cross": false,
      "death_cross": false
    },
    {
      "symbol": "ASR",
      "last_close": 312.56,
      "sma150": 315.21,
      "distance_percent": -0.84,
      "atr": 6.57,
      "atr_percent": 2.14,
      "last_volume": 44766,
      "avg_volume_14d": 51150,
      "golden_cross": false,
      "death_cross": false
    },
    {
      "symbol": "PHG",
      "last_close": 26.13,
      "sma150": 26.35,
      "distance_percent": -0.85,
      "atr": 0.3,
      "atr_percent": 1.09,
      "last_volume": 525923,
      "avg_volume_14d": 687114,
      "golden_cross": false,
      "death_cross": false
    },
    {
      "symbol": "GGG",
      "last_close": 83.16,
      "sma150": 83.91,
      "distance_percent": -0.9,
      "atr": 1.46,
      "atr_percent": 1.76,
      "last_volume": 542040,
      "avg_volume_14d": 786357,
      "golden_cross": false,
      "death_cross": false
    },
    {
      "symbol": "BLK",
      "last_close": 1065.0,
      "sma150": 1075.2,
      "distance_percent": -0.95,
      "atr": 19.3,
      "atr_percent": 1.81,
      "last_volume": 441662,
      "avg_volume_14d": 597457,
      "golden_cross": false,
      "death_cross": false
    },
    {
      "symbol": "EE",
      "last_close": 26.3,
      "sma150": 26.56,
      "distance_percent": -0.98,
      "atr": 0.78,
      "atr_percent": 2.81,
      "last_volume": 225492,
      "avg_volume_14d": 332157,
      "golden_cross": false,
      "death_cross": false
    },
    {
      "symbol": "DKS",
      "last_close": 207.96,
      "sma150": 210.1,
      "distance_percent": -1.02,
      "atr": 8.05,
      "atr_percent": 3.72,
      "last_volume": 1136764,
      "avg_volume_14d": 1777357,
      "golden_cross": false,
      "death_cross": false
    },
    {
      "symbol": "TBB",
      "last_close": 22.21,
      "sma150": 22.44,
      "distance_percent": -1.03,
      "atr": 0.2,
      "atr_percent": 0.91,
      "last_volume": 66909,
      "avg_volume_14d": 103350,
      "golden_cross": false,
      "death_cross": false
    },
    {
      "symbol": "KFY",
      "last_close": 69.05,
      "sma150": 69.78,
      "distance_percent": -1.04,
      "atr": 1.5,
      "atr_percent": 2.23,
      "last_volume": 391639,
      "avg_volume_14d": 539592,
      "golden_cross": false,
      "death_cross": false
    },
    {
      "symbol": "TAC",
      "last_close": 12.81,
      "sma150": 12.95,
      "distance_percent": -1.06,
      "atr": 0.52,
      "atr_percent": 3.69,
      "last_volume": 1780673,
      "avg_volume_14d": 1158778,
      "golden_cross": false,
      "death_cross": false
    },
    {
      "symbol": "XEL",
      "last_close": 73.14,
      "sma150": 73.94,
      "distance_percent": -1.08,
      "atr": 1.47,
      "atr_percent": 1.92,
      "last_volume": 9061702,
      "avg_volume_14d": 4923050,
      "golden_cross": false,
      "death_cross": false
    },
    {
      "symbol": "AMZN",
      "last_close": 221.27,
      "sma150": 223.75,
      "distance_percent": -1.11,
      "atr": 4.11,
      "atr_percent": 1.8,
      "last_volume": 40369357,
      "avg_volume_14d": 36564328,
      "golden_cross": false,
      "death_cross": false
    },
    {
      "symbol": "SITE",
      "last_close": 127.55,
      "sma150": 129.11,
      "distance_percent": -1.21,
      "atr": 4.59,
      "atr_percent": 3.53,
      "last_volume": 372309,
      "avg_volume_14d": 536528,
      "golden_cross": false,
      "death_cross": false
    },
    {
      "symbol": "SCI",
      "last_close": 78.5,
      "sma150": 79.51,
      "distance_percent": -1.27,
      "atr": 1.56,
      "atr_percent": 2.0,
      "last_volume": 811285,
      "avg_volume_14d": 942692,
      "golden_cross": false,
      "death_cross": false
    },
    {
      "symbol": "DTB",
      "last_close": 17.33,
      "sma150": 17.56,
      "distance_percent": -1.32,
      "atr": 0.17,
      "atr_percent": 0.96,
      "last_volume": 32490,
      "avg_volume_14d": 28650,
      "golden_cross": false,
      "death_cross": false
    },
    {
      "symbol": "NNN",
      "last_close": 40.68,
      "sma150": 41.24,
      "distance_percent": -1.35,
      "atr": 0.57,
      "atr_percent": 1.4,
      "last_volume": 996887,
      "avg_volume_14d": 1413192,
      "golden_cross": false,
      "death_cross": true
    },
    {
      "symbol": "PNR",
      "last_close": 103.66,
      "sma150": 105.1,
      "distance_percent": -1.37,
      "atr": 2.24,
      "atr_percent": 2.14,
      "last_volume": 779080,
      "avg_volume_14d": 1140714,
      "golden_cross": false,
      "death_cross": false
    },
    {
      "symbol": "OVV",
      "last_close": 38.82,
      "sma150": 39.36,
      "distance_percent": -1.38,
      "atr": 1.13,
      "atr_percent": 2.78,
      "last_volume": 3536420,
      "avg_volume_14d": 3007728,
      "golden_cross": false,
      "death_cross": false
    },
    {
      "symbol": "RRX",
      "last_close": 141.63,
      "sma150": 143.64,
      "distance_percent": -1.4,
      "atr": 5.76,
      "atr_percent": 3.95,
      "last_volume": 640176,
      "avg_volume_14d": 826400,
      "golden_cross": false,
      "death_cross": false
    },
    {
      "symbol": "KMI",
      "last_close": 26.65,
      "sma150": 27.03,
      "distance_percent": -1.41,
      "atr": 0.49,
      "atr_percent": 1.8,
      "last_volume": 9343431,
      "avg_volume_14d": 11830842,
      "golden_cross": false,
      "death_cross": true
    },
    {
      "symbol": "NCLH",
      "last_close": 21.54,
      "sma150": 21.86,
      "distance_percent": -1.44,
      "atr": 0.65,
      "atr_percent": 3.28,
      "last_volume": 14402547,
      "avg_volume_14d": 17074042,
      "golden_cross": false,
      "death_cross": false
    },
    {
      "symbol": "CMS",
      "last_close": 70.26,
      "sma150": 71.3,
      "distance_percent": -1.45,
      "atr": 1.05,
      "atr_percent": 1.47,
      "last_volume": 1903977,
      "avg_volume_14d": 1930892,
      "golden_cross": false,
      "death_cross": false
    },
    {
      "symbol": "PBA",
      "last_close": 37.36,
      "sma150": 37.94,
      "distance_percent": -1.52,
      "atr": 0.64,
      "atr_percent": 1.65,
      "last_volume": 1473246,
      "avg_volume_14d": 1274235,
      "golden_cross": false,
      "death_cross": false
    },
    {
      "symbol": "PJT",
      "last_close": 168.4,
      "sma150": 171.01,
      "distance_percent": -1.52,
      "atr": 4.45,
      "atr_percent": 2.6,
      "last_volume": 145578,
      "avg_volume_14d": 260714,
      "golden_cross": false,
      "death_cross": false
    },
    {
      "symbol": "AM",
      "last_close": 17.66,
      "sma150": 17.94,
      "distance_percent": -1.54,
      "atr": 0.38,
      "atr_percent": 2.09,
      "last_volume": 2373886,
      "avg_volume_14d": 2286764,
      "golden_cross": false,
      "death_cross": false
    },
    {
      "symbol": "SYY",
      "last_close": 75.75,
      "sma150": 76.94,
      "distance_percent": -1.54,
      "atr": 1.24,
      "atr_percent": 1.67,
      "last_volume": 1389220,
      "avg_volume_14d": 3186407,
      "golden_cross": false,
      "death_cross": false
    },
    {
      "symbol": "MPC",
      "last_close": 174.5,
      "sma150": 177.39,
      "distance_percent": -1.63,
      "atr": 4.45,
      "atr_percent": 2.36,
      "last_volume": 2338786,
      "avg_volume_14d": 2072464,
      "golden_cross": false,
      "death_cross": false
    },
    {
      "symbol": "SBUX",
      "last_close": 85.21,
      "sma150": 86.63,
      "distance_percent": -1.64,
      "atr": 1.84,
      "atr_percent": 2.17,
      "last_volume": 7807531,
      "avg_volume_14d": 8900121,
      "golden_cross": false,
      "death_cross": false
    },
    {
      "symbol": "RITM",
      "last_close": 11.15,
      "sma150": 11.34,
      "distance_percent": -1.68,
      "atr": 0.17,
      "atr_percent": 1.56,
      "last_volume": 4213373,
      "avg_volume_14d": 5004342,
      "golden_cross": false,
      "death_cross": false
    },
    {
      "symbol": "PFGC",
      "last_close": 94.82,
      "sma150": 96.45,
      "distance_percent": -1.69,
      "atr": 2.0,
      "atr_percent": 2.13,
      "last_volume": 672359,
      "avg_volume_14d": 1603478,
      "golden_cross": false,
      "death_cross": false
    },
    {
      "symbol": "GEN",
      "last_close": 27.9,
      "sma150": 28.4,
      "distance_percent": -1.79,
      "atr": 0.53,
      "atr_percent": 1.95,
      "last_volume": 5548855,
      "avg_volume_14d": 3804264,
      "golden_cross": false,
      "death_cross": false
    },
    {
      "symbol": "DUK",
      "last_close": 117.43,
      "sma150": 119.57,
      "distance_percent": -1.79,
      "atr": 1.76,
      "atr_percent": 1.5,
      "last_volume": 3520490,
      "avg_volume_14d": 3383035,
      "golden_cross": false,
      "death_cross": false
    },
    {
      "symbol": "HEI",
      "last_close": 306.89,
      "sma150": 312.64,
      "distance_percent": -1.84,
      "atr": 6.53,
      "atr_percent": 2.1,
      "last_volume": 383337,
      "avg_volume_14d": 394428,
      "golden_cross": false,
      "death_cross": false
    },
    {
      "symbol": "BBY",
      "last_close": 71.45,
      "sma150": 72.79,
      "distance_percent": -1.84,
      "atr": 2.06,
      "atr_percent": 2.77,
      "last_volume": 3663816,
      "avg_volume_14d": 4947692,
      "golden_cross": false,
      "death_cross": false
    },
    {
      "symbol": "PEG",
      "last_close": 79.91,
      "sma150": 81.41,
      "distance_percent": -1.84,
      "atr": 1.27,
      "atr_percent": 1.59,
      "last_volume": 2541119,
      "avg_volume_14d": 3001542,
      "golden_cross": false,
      "death_cross": false
    },
    {
      "symbol": "KKRS",
      "last_close": 17.41,
      "sma150": 17.76,
      "distance_percent": -2.0,
      "atr": 0.15,
      "atr_percent": 0.85,
      "last_volume": 18664,
      "avg_volume_14d": 45942,
      "golden_cross": false,
      "death_cross": false
    },
    {
      "symbol": "KIM",
      "last_close": 20.45,
      "sma150": 20.87,
      "distance_percent": -2.0,
      "atr": 0.3,
      "atr_percent": 1.51,
      "last_volume": 2319212,
      "avg_volume_14d": 4133150,
      "golden_cross": false,
      "death_cross": true
    },
    {
      "symbol": "NVR",
      "last_close": 7472.55,
      "sma150": 7626.13,
      "distance_percent": -2.01,
      "atr": 139.09,
      "atr_percent": 1.85,
      "last_volume": 14328,
      "avg_volume_14d": 18142,
      "golden_cross": false,
      "death_cross": false
    },
    {
      "symbol": "BX",
      "last_close": 153.19,
      "sma150": 156.35,
      "distance_percent": -2.02,
      "atr": 3.91,
      "atr_percent": 2.58,
      "last_volume": 2864392,
      "avg_volume_14d": 3723100,
      "golden_cross": false,
      "death_cross": false
    },
    {
      "symbol": "EAT",
      "last_close": 145.51,
      "sma150": 148.58,
      "distance_percent": -2.06,
      "atr": 6.19,
      "atr_percent": 4.29,
      "last_volume": 1283468,
      "avg_volume_14d": 1340042,
      "golden_cross": false,
      "death_cross": false
    },
    {
      "symbol": "CRWD",
      "last_close": 470.02,
      "sma150": 480.06,
      "distance_percent": -2.09,
      "atr": 17.1,
      "atr_percent": 3.37,
      "last_volume": 2278241,
      "avg_volume_14d": 2550750,
      "golden_cross": false,
      "death_cross": false
    },
    {
      "symbol": "SNN",
      "last_close": 32.54,
      "sma150": 33.25,
      "distance_percent": -2.13,
      "atr": 0.42,
      "atr_percent": 1.28,
      "last_volume": 244079,
      "avg_volume_14d": 539928,
      "golden_cross": false,
      "death_cross": false
    },
    {
      "symbol": "LPL",
      "last_close": 4.1,
      "sma150": 4.19,
      "distance_percent": -2.14,
      "atr": 0.07,
      "atr_percent": 1.54,
      "last_volume": 321042,
      "avg_volume_14d": 315021,
      "golden_cross": false,
      "death_cross": false
    },
    {
      "symbol": "MAS",
      "last_close": 65.11,
      "sma150": 66.57,
      "distance_percent": -2.19,
      "atr": 1.55,
      "atr_percent": 2.41,
      "last_volume": 1841995,
      "avg_volume_14d": 2518592,
      "golden_cross": false,
      "death_cross": false
    },
    {
      "symbol": "ECL",
      "last_close": 261.89,
      "sma150": 267.83,
      "distance_percent": -2.22,
      "atr": 4.59,
      "atr_percent": 1.75,
      "last_volume": 868818,
      "avg_volume_14d": 1451514,
      "golden_cross": false,
      "death_cross": false
    },
    {
      "symbol": "EBAY",
      "last_close": 82.71,
      "sma150": 84.65,
      "distance_percent": -2.29,
      "atr": 1.88,
      "atr_percent": 2.27,
      "last_volume": 4234393,
      "avg_volume_14d": 3894578,
      "golden_cross": false,
      "death_cross": false
    },
    {
      "symbol": "ANET",
      "last_close": 122.36,
      "sma150": 125.23,
      "distance_percent": -2.3,
      "atr": 4.7,
      "atr_percent": 3.67,
      "last_volume": 8221760,
      "avg_volume_14d": 5886985,
      "golden_cross": false,
      "death_cross": false
    },
    {
      "symbol": "PDI",
      "last_close": 17.66,
      "sma150": 18.08,
      "distance_percent": -2.33,
      "atr": 0.11,
      "atr_percent": 0.64,
      "last_volume": 3249165,
      "avg_volume_14d": 2669100,
      "golden_cross": false,
      "death_cross": false
    },
    {
      "symbol": "PBF",
      "last_close": 26.61,
      "sma150": 27.27,
      "distance_percent": -2.41,
      "atr": 1.58,
      "atr_percent": 5.0,
      "last_volume": 2808421,
      "avg_volume_14d": 2774428,
      "golden_cross": false,
      "death_cross": false
    },
    {
      "symbol": "ADT",
      "last_close": 8.15,
      "sma150": 8.35,
      "distance_percent": -2.44,
      "atr": 0.14,
      "atr_percent": 1.68,
      "last_volume": 5200412,
      "avg_volume_14d": 6370650,
      "golden_cross": false,
      "death_cross": false
    },
    {
      "symbol": "DELL",
      "last_close": 127.89,
      "sma150": 131.1,
      "distance_percent": -2.45,
      "atr": 4.75,
      "atr_percent": 3.51,
      "last_volume": 5248319,
      "avg_volume_14d": 6437078,
      "golden_cross": false,
      "death_cross": false
    },
    {
      "symbol": "NFG",
      "last_close": 82.1,
      "sma150": 84.22,
      "distance_percent": -2.51,
      "atr": 1.23,
      "atr_percent": 1.5,
      "last_volume": 243170,
      "avg_volume_14d": 548114,
      "golden_cross": false,
      "death_cross": true
    },
    {
      "symbol": "BDC",
      "last_close": 116.17,
      "sma150": 119.17,
      "distance_percent": -2.51,
      "atr": 3.19,
      "atr_percent": 2.66,
      "last_volume": 198311,
      "avg_volume_14d": 241992,
      "golden_cross": false,
      "death_cross": false
    },
    {
      "symbol": "SSD",
      "last_close": 166.48,
      "sma150": 170.78,
      "distance_percent": -2.52,
      "atr": 4.43,
      "atr_percent": 2.63,
      "last_volume": 189199,
      "avg_volume_14d": 305835,
      "golden_cross": false,
      "death_cross": false
    },
    {
      "symbol": "VLTO",
      "last_close": 100.05,
      "sma150": 102.64,
      "distance_percent": -2.53,
      "atr": 1.67,
      "atr_percent": 1.67,
      "last_volume": 1195386,
      "avg_volume_14d": 1553335,
      "golden_cross": false,
      "death_cross": true
    },
    {
      "symbol": "MNSO",
      "last_close": 20.09,
      "sma150": 20.62,
      "distance_percent": -2.56,
      "atr": 0.36,
      "atr_percent": 1.82,
      "last_volume": 1170496,
      "avg_volume_14d": 486757,
      "golden_cross": false,
      "death_cross": false
    },
    {
      "symbol": "MRP",
      "last_close": 29.78,
      "sma150": 30.58,
      "distance_percent": -2.62,
      "atr": 0.86,
      "atr_percent": 2.75,
      "last_volume": 2985266,
      "avg_volume_14d": 2810692,
      "golden_cross": false,
      "death_cross": false
    },
    {
      "symbol": "TMHC",
      "last_close": 61.02,
      "sma150": 62.68,
      "distance_percent": -2.64,
      "atr": 1.54,
      "atr_percent": 2.48,
      "last_volume": 747699,
      "avg_volume_14d": 948607,
      "golden_cross": false,
      "death_cross": false
    },
    {
      "symbol": "HAFN",
      "last_close": 5.59,
      "sma150": 5.75,
      "distance_percent": -2.72,
      "atr": 0.1,
      "atr_percent": 1.73,
      "last_volume": 692165,
      "avg_volume_14d": 1239528,
      "golden_cross": false,
      "death_cross": false
    },
    {
      "symbol": "MTCH",
      "last_close": 32.51,
      "sma150": 33.43,
      "distance_percent": -2.74,
      "atr": 0.74,
      "atr_percent": 2.21,
      "last_volume": 3992841,
      "avg_volume_14d": 2931657,
      "golden_cross": false,
      "death_cross": false
    },
    {
      "symbol": "MO",
      "last_close": 59.18,
      "sma150": 60.91,
      "distance_percent": -2.84,
      "atr": 0.7,
      "atr_percent": 1.2,
      "last_volume": 6203548,
      "avg_volume_14d": 7399850,
      "golden_cross": false,
      "death_cross": false
    },
    {
      "symbol": "WEC",
      "last_close": 104.76,
      "sma150": 107.88,
      "distance_percent": -2.89,
      "atr": 1.53,
      "atr_percent": 1.45,
      "last_volume": 1273834,
      "avg_volume_14d": 2122492,
      "golden_cross": false,
      "death_cross": false
    },
    {
      "symbol": "WEX",
      "last_close": 150.03,
      "sma150": 154.53,
      "distance_percent": -2.91,
      "atr": 4.25,
      "atr_percent": 2.81,
      "last_volume": 294301,
      "avg_volume_14d": 358171,
      "golden_cross": false,
      "death_cross": false
    },
    {
      "symbol": "ET",
      "last_close": 16.39,
      "sma150": 16.89,
      "distance_percent": -2.98,
      "atr": 0.21,
      "atr_percent": 1.27,
      "last_volume": 13945895,
      "avg_volume_14d": 13035078,
      "golden_cross": false,
      "death_cross": false
    },
    {
      "symbol": "RDY",
      "last_close": 13.93,
      "sma150": 14.36,
      "distance_percent": -3.02,
      "atr": 0.16,
      "atr_percent": 1.13,
      "last_volume": 776848,
      "avg_volume_14d": 1157985,
      "golden_cross": false,
      "death_cross": false
    },
    {
      "symbol": "NPO",
      "last_close": 205.19,
      "sma150": 211.59,
      "distance_percent": -3.02,
      "atr": 6.74,
      "atr_percent": 3.07,
      "last_volume": 234886,
      "avg_volume_14d": 163350,
      "golden_cross": false,
      "death_cross": false
    },
    {
      "symbol": "LH",
      "last_close": 255.81,
      "sma150": 263.97,
      "distance_percent": -3.09,
      "atr": 4.66,
      "atr_percent": 1.78,
      "last_volume": 475576,
      "avg_volume_14d": 578464,
      "golden_cross": false,
      "death_cross": false
    },
    {
      "symbol": "MTH",
      "last_close": 68.29,
      "sma150": 70.49,
      "distance_percent": -3.11,
      "atr": 1.94,
      "atr_percent": 2.7,
      "last_volume": 854801,
      "avg_volume_14d": 673564,
      "golden_cross": false,
      "death_cross": false
    },
    {
      "symbol": "DIS",
      "last_close": 110.63,
      "sma150": 114.25,
      "distance_percent": -3.17,
      "atr": 2.08,
      "atr_percent": 1.93,
      "last_volume": 11515893,
      "avg_volume_14d": 11422557,
      "golden_cross": false,
      "death_cross": true
    },
    {
      "symbol": "NEU",
      "last_close": 721.01,
      "sma150": 744.98,
      "distance_percent": -3.22,
      "atr": 19.91,
      "atr_percent": 2.65,
      "last_volume": 93883,
      "avg_volume_14d": 105221,
      "golden_cross": false,
      "death_cross": false
    },
    {
      "symbol": "TSCO",
      "last_close": 53.49,
      "sma150": 55.28,
      "distance_percent": -3.24,
      "atr": 1.08,
      "atr_percent": 2.03,
      "last_volume": 5203698,
      "avg_volume_14d": 4749314,
      "golden_cross": false,
      "death_cross": false
    },
    {
      "symbol": "ADSK",
      "last_close": 292.97,
      "sma150": 302.81,
      "distance_percent": -3.25,
      "atr": 6.28,
      "atr_percent": 2.08,
      "last_volume": 1290395,
      "avg_volume_14d": 1759242,
      "golden_cross": false,
      "death_cross": false
    },
    {
      "symbol": "SUZ",
      "last_close": 8.99,
      "sma150": 9.3,
      "distance_percent": -3.29,
      "atr": 0.16,
      "atr_percent": 1.76,
      "last_volume": 2338757,
      "avg_volume_14d": 2500864,
      "golden_cross": false,
      "death_cross": false
    },
    {
      "symbol": "QGEN",
      "last_close": 45.21,
      "sma150": 46.77,
      "distance_percent": -3.33,
      "atr": 0.62,
      "atr_percent": 1.35,
      "last_volume": 1274856,
      "avg_volume_14d": 1161528,
      "golden_cross": false,
      "death_cross": false
    },
    {
      "symbol": "IR",
      "last_close": 78.12,
      "sma150": 80.83,
      "distance_percent": -3.35,
      "atr": 1.77,
      "atr_percent": 2.21,
      "last_volume": 2246553,
      "avg_volume_14d": 2301707,
      "golden_cross": false,
      "death_cross": false
    },
    {
      "symbol": "APAM",
      "last_close": 41.59,
      "sma150": 43.05,
      "distance_percent": -3.38,
      "atr": 0.88,
      "atr_percent": 2.1,
      "last_volume": 413260,
      "avg_volume_14d": 566442,
      "golden_cross": false,
      "death_cross": false
    },
    {
      "symbol": "BA",
      "last_close": 206.33,
      "sma150": 213.57,
      "distance_percent": -3.39,
      "atr": 4.8,
      "atr_percent": 2.38,
      "last_volume": 5980196,
      "avg_volume_14d": 9443878,
      "golden_cross": false,
      "death_cross": true
    },
    {
      "symbol": "WDS",
      "last_close": 15.45,
      "sma150": 16.01,
      "distance_percent": -3.49,
      "atr": 0.24,
      "atr_percent": 1.48,
      "last_volume": 1775201,
      "avg_volume_14d": 612935,
      "golden_cross": false,
      "death_cross": false
    },
    {
      "symbol": "FSS",
      "last_close": 109.55,
      "sma150": 113.54,
      "distance_percent": -3.51,
      "atr": 2.61,
      "atr_percent": 2.35,
      "last_volume": 258176,
      "avg_volume_14d": 692600,
      "golden_cross": false,
      "death_cross": false
    },
    {
      "symbol": "PBR",
      "last_close": 11.77,
      "sma150": 12.22,
      "distance_percent": -3.65,
      "atr": 0.26,
      "atr_percent": 2.1,
      "last_volume": 22935669,
      "avg_volume_14d": 18238914,
      "golden_cross": false,
      "death_cross": false
    },
    {
      "symbol": "CTVA",
      "last_close": 66.43,
      "sma150": 69.01,
      "distance_percent": -3.74,
      "atr": 1.2,
      "atr_percent": 1.82,
      "last_volume": 2533046,
      "avg_volume_14d": 3735585,
      "golden_cross": false,
      "death_cross": false
    },
    {
      "symbol": "NKE",
      "last_close": 65.69,
      "sma150": 68.24,
      "distance_percent": -3.74,
      "atr": 1.61,
      "atr_percent": 2.45,
      "last_volume": 10886133,
      "avg_volume_14d": 12750935,
      "golden_cross": false,
      "death_cross": false
    },
    {
      "symbol": "CRGY",
      "last_close": 8.5,
      "sma150": 8.84,
      "distance_percent": -3.8,
      "atr": 0.34,
      "atr_percent": 3.6,
      "last_volume": 7482625,
      "avg_volume_14d": 4878642,
      "golden_cross": false,
      "death_cross": false
    },
    {
      "symbol": "SXT",
      "last_close": 96.56,
      "sma150": 100.44,
      "distance_percent": -3.87,
      "atr": 2.73,
      "atr_percent": 2.9,
      "last_volume": 341001,
      "avg_volume_14d": 283657,
      "golden_cross": false,
      "death_cross": false
    },
    {
      "symbol": "VNT",
      "last_close": 37.56,
      "sma150": 39.08,
      "distance_percent": -3.88,
      "atr": 0.65,
      "atr_percent": 1.78,
      "last_volume": 1027210,
      "avg_volume_14d": 1188514,
      "golden_cross": false,
      "death_cross": false
    },
    {
      "symbol": "SNOW",
      "last_close": 216.29,
      "sma150": 225.05,
      "distance_percent": -3.89,
      "atr": 7.66,
      "atr_percent": 3.3,
      "last_volume": 2423836,
      "avg_volume_14d": 7620507,
      "golden_cross": false,
      "death_cross": false
    }
  ],
  "failed_tickers": [],
  "filtered_by_sma": [
    "A",
    "AA",
    "AAP",
    "AAPL",
    "ABBV",
    "ABCB",
    "ABEV",
    "ABM",
    "ABNB",
    "ABR",
    "ABT",
    "ACA",
    "ACGL",
    "ACHR",
    "ACI",
    "ACM",
    "ACN",
    "AD",
    "ADBE",
    "ADC",
    "ADI",
    "ADP",
    "AEM",
    "AEO",
    "AEP",
    "AER",
    "AES",
    "AFG",
    "AFL",
    "AG",
    "AGI",
    "AGO",
    "AGX",
    "AHR",
    "AI",
    "AIG",
    "AIR",
    "AIZ",
    "AJG",
    "AKAM",
    "AKR",
    "AL",
    "ALB",
    "ALC",
    "ALG",
    "ALGN",
    "ALK",
    "ALLY",
    "ALSN",
    "AMAT",
    "AMBP",
    "AMCR",
    "AMD",
    "AME",
    "AMG",
    "AMGN",
    "AMH",
    "AMP",
    "AMR",
    "AMRC",
    "AMT",
    "AMTM",
    "AMX",
    "ANF",
    "AON",
    "APA",
    "APD",
    "APG",
    "APH",
    "APLE",
    "APO",
    "APP",
    "AQN",
    "AR",
    "ARDT",
    "ARE",
    "ARMK",
    "AROC",
    "ARW",
    "AS",
    "ASAN",
    "ASB",
    "ASGN",
    "ASH",
    "ASX",
    "ATGE",
    "ATHM",
    "ATI",
    "ATKR",
    "ATMU",
    "ATR",
    "ATS",
    "AU",
    "AUB",
    "AVA",
    "AVAL",
    "AVB",
    "AVNT",
    "AVTR",
    "AVY",
    "AWK",
    "AWR",
    "AX",
    "AXON",
    "AXP",
    "AXS",
    "AXTA",
    "AYI",
    "AZO",
    "AZZ",
    "B",
    "BABA",
    "BAC",
    "BAH",
    "BALL",
    "BAM",
    "BANC",
    "BAP",
    "BAX",
    "BBAI",
    "BBD",
    "BBDO",
    "BBT",
    "BBU",
    "BBUC",
    "BBVA",
    "BBWI",
    "BC",
    "BCC",
    "BCH",
    "BCO",
    "BCS",
    "BDX",
    "BE",
    "BEKE",
    "BEPC",
    "BEPJ",
    "BFAM",
    "BFH",
    "BG",
    "BHC",
    "BHP",
    "BIIB",
    "BILL",
    "BIO",
    "BIPC",
    "BIRK",
    "BJ",
    "BK",
    "BKD",
    "BKE",
    "BKH",
    "BKU",
    "BLCO",
    "BLD",
    "BLDR",
    "BMA",
    "BMI",
    "BMO",
    "BMY",
    "BNS",
    "BOH",
    "BOOT",
    "BOX",
    "BP",
    "BR",
    "BRBR",
    "BRC",
    "BRO",
    "BROS",
    "BRSL",
    "BSAC",
    "BSBR",
    "BSM",
    "BSX",
    "BTI",
    "BTU",
    "BUD",
    "BUR",
    "BVN",
    "BWA",
    "BWNB",
    "BXMT",
    "BYD",
    "C",
    "CAAP",
    "CACI",
    "CADE",
    "CAG",
    "CAH",
    "CALX",
    "CARR",
    "CAT",
    "CAVA",
    "CB",
    "CBOE",
    "CBRE",
    "CBT",
    "CBU",
    "CBZ",
    "CC",
    "CCI",
    "CCJ",
    "CCK",
    "CDE",
    "CDNS",
    "CDW",
    "CE",
    "CF",
    "CFG",
    "CGAU",
    "CHD",
    "CHE",
    "CHH",
    "CHRW",
    "CHT",
    "CHTR",
    "CHWY",
    "CI",
    "CIB",
    "CIEN",
    "CII",
    "CINF",
    "CIVI",
    "CL",
    "CLF",
    "CLS",
    "CLVT",
    "CLX",
    "CM",
    "CMA",
    "CMC",
    "CMCM",
    "CMCSA",
    "CME",
    "CMG",
    "CMI",
    "CMPO",
    "CNA",
    "CNC",
    "CNH",
    "CNI",
    "CNK",
    "CNM",
    "CNO",
    "CNR",
    "CNS",
    "CNX",
    "COF",
    "COHR",
    "COIN",
    "COLD",
    "COMP",
    "CON",
    "COO",
    "COP",
    "COR",
    "COST",
    "COTY",
    "CP",
    "CPAY",
    "CPB",
    "CPNG",
    "CPRI",
    "CPRT",
    "CPT",
    "CQP",
    "CRBG",
    "CRC",
    "CRH",
    "CRK",
    "CRL",
    "CRM",
    "CRS",
    "CSAN",
    "CSCO",
    "CSGP",
    "CSL",
    "CSTM",
    "CSW",
    "CSX",
    "CTAS",
    "CTRA",
    "CTRE",
    "CTSH",
    "CUBE",
    "CUBI",
    "CUZ",
    "CVE",
    "CVI",
    "CVNA",
    "CVS",
    "CW",
    "CWAN",
    "CWEN",
    "CWK",
    "CWT",
    "CX",
    "CXT",
    "DAL",
    "DAN",
    "DASH",
    "DAY",
    "DB",
    "DBD",
    "DBRG",
    "DCI",
    "DD",
    "DDOG",
    "DDS",
    "DE",
    "DECK",
    "DEI",
    "DEO",
    "DFH",
    "DG",
    "DHR",
    "DK",
    "DLB",
    "DLR",
    "DLTR",
    "DOC",
    "DOCN",
    "DOCS",
    "DOV",
    "DOW",
    "DPZ",
    "DRD",
    "DRI",
    "DT",
    "DTE",
    "DTM",
    "DVA",
    "DVN",
    "DXC",
    "DXCM",
    "DY",
    "E",
    "EA",
    "EBR",
    "ECG",
    "ED",
    "EDU",
    "EFX",
    "EG",
    "EGO",
    "EGP",
    "EHC",
    "EIX",
    "EL",
    "ELAN",
    "ELF",
    "ELP",
    "ELPC",
    "ELS",
    "ELV",
    "EMN",
    "ENIC",
    "ENS",
    "ENVA",
    "EOG",
    "EPAC",
    "EPAM",
    "EPR",
    "EPRT",
    "EQH",
    "EQIX",
    "EQNR",
    "EQR",
    "ERIE",
    "ERJ",
    "ERO",
    "ESAB",
    "ESNT",
    "ESS",
    "ESTC",
    "ETN",
    "ETSY",
    "EVR",
    "EW",
    "EXC",
    "EXK",
    "EXP",
    "EXPD",
    "EXPE",
    "EXR",
    "F",
    "FAF",
    "FANG",
    "FAST",
    "FBIN",
    "FBK",
    "FBP",
    "FCN",
    "FCPT",
    "FCX",
    "FDS",
    "FDX",
    "FFIV",
    "FHI",
    "FHN",
    "FI",
    "FICO",
    "FIHL",
    "FIS",
    "FITB",
    "FIX",
    "FLG",
    "FLO",
    "FLR",
    "FLS",
    "FLUT",
    "FMC",
    "FMS",
    "FMX",
    "FN",
    "FNB",
    "FND",
    "FNF",
    "FNV",
    "FOUR",
    "FOX",
    "FOXA",
    "FR",
    "FRO",
    "FRT",
    "FSK",
    "FSLR",
    "FSM",
    "FTI",
    "FTNT",
    "FTS",
    "FTV",
    "FUL",
    "FUN",
    "G",
    "GAP",
    "GATX",
    "GBTG",
    "GD",
    "GDDY",
    "GE",
    "GEF",
    "GEHC",
    "GENI",
    "GEO",
    "GEV",
    "GFI",
    "GFL",
    "GGB",
    "GHC",
    "GIB",
    "GIL",
    "GILD",
    "GIS",
    "GKOS",
    "GL",
    "GLOB",
    "GLW",
    "GM",
    "GME",
    "GMED",
    "GNRC",
    "GNW",
    "GOLF",
    "GOOG",
    "GOOGL",
    "GPI",
    "GPK",
    "GPOR",
    "GRMN",
    "GRND",
    "GS",
    "GSK",
    "GTES",
    "GTLS",
    "GVA",
    "GWRE",
    "GWW",
    "GXO",
    "H",
    "HAE",
    "HAL",
    "HAS",
    "HASI",
    "HBAN",
    "HBM",
    "HCA",
    "HCC",
    "HCI",
    "HD",
    "HDB",
    "HESM",
    "HGTY",
    "HGV",
    "HHH",
    "HI",
    "HIG",
    "HII",
    "HIMS",
    "HIW",
    "HL",
    "HLI",
    "HLN",
    "HLT",
    "HMC",
    "HMY",
    "HNI",
    "HOG",
    "HOLX",
    "HON",
    "HOOD",
    "HP",
    "HPE",
    "HPQ",
    "HRB",
    "HRI",
    "HRL",
    "HSBC",
    "HSIC",
    "HST",
    "HSY",
    "HTGC",
    "HTH",
    "HUBS",
    "HXL",
    "IAG",
    "IBM",
    "IBN",
    "IBP",
    "ICE",
    "ICL",
    "IDXX",
    "IEX",
    "IFF",
    "IFS",
    "IHG",
    "IHS",
    "INCY",
    "INFY",
    "ING",
    "INGM",
    "INGR",
    "INSP",
    "INSW",
    "INTC",
    "INTU",
    "INVH",
    "IONQ",
    "IOT",
    "IP",
    "IQV",
    "IREN",
    "IRM",
    "IRT",
    "ISRG",
    "IT",
    "ITGR",
    "IVZ",
    "IX",
    "J",
    "JBHT",
    "JBL",
    "JBTM",
    "JCI",
    "JEF",
    "JHG",
    "JHX",
    "JKHY",
    "JLL",
    "JNJ",
    "JOBY",
    "JOE",
    "JPM",
    "JXN",
    "KAI",
    "KAR",
    "KBH",
    "KBR",
    "KD",
    "KDP",
    "KEN",
    "KEP",
    "KEX",
    "KEY",
    "KEYS",
    "KGC",
    "KGS",
    "KHC",
    "KLAC",
    "KMB",
    "KMPR",
    "KMX",
    "KN",
    "KNF",
    "KNSL",
    "KNTK",
    "KNX",
    "KOF",
    "KR",
    "KRG",
    "KRMN",
    "KT",
    "KTB",
    "KVUE",
    "KVYO",
    "KWR",
    "L",
    "LAC",
    "LAD",
    "LB",
    "LCII",
    "LEA",
    "LEN",
    "LEVI",
    "LII",
    "LIN",
    "LKQ",
    "LLY",
    "LMND",
    "LNC",
    "LNG",
    "LOAR",
    "LOW",
    "LPX",
    "LRCX",
    "LRN",
    "LTH",
    "LTM",
    "LU",
    "LULU",
    "LUMN",
    "LUV",
    "LVS",
    "LW",
    "LXP",
    "LYB",
    "LYG",
    "LYV",
    "M",
    "MA",
    "MAA",
    "MAC",
    "MANU",
    "MAR",
    "MATX",
    "MC",
    "MCD",
    "MCK",
    "MCY",
    "MDLZ",
    "MDT",
    "MDU",
    "MET",
    "META",
    "MFC",
    "MFG",
    "MGA",
    "MGM",
    "MGY",
    "MHK",
    "MKC",
    "MKL",
    "MLI",
    "MLM",
    "MMC",
    "MMM",
    "MMS",
    "MNST",
    "MOH",
    "MOS",
    "MP",
    "MPLX",
    "MPW",
    "MPWR",
    "MRK",
    "MRNA",
    "MS",
    "MSA",
    "MSCI",
    "MSFT",
    "MSGE",
    "MSGS",
    "MSI",
    "MSTR",
    "MSTY",
    "MT",
    "MTB",
    "MTD",
    "MTDR",
    "MTG",
    "MTRN",
    "MTZ",
    "MU",
    "MUFG",
    "MUR",
    "MUSA",
    "MWA",
    "NATL",
    "NDAQ",
    "NDSN",
    "NEE",
    "NEM",
    "NET",
    "NFLX",
    "NGG",
    "NGVT",
    "NHI",
    "NIO",
    "NJR",
    "NLY",
    "NMR",
    "NNE",
    "NNI",
    "NOG",
    "NOK",
    "NOV",
    "NOW",
    "NRG",
    "NSA",
    "NSC",
    "NTR",
    "NTRS",
    "NU",
    "NUE",
    "NVO",
    "NVS",
    "NVST",
    "NVT",
    "NWG",
    "NWS",
    "NWSA",
    "NXE",
    "NYT",
    "OBDC",
    "OC",
    "ODFL",
    "OGE",
    "OGN",
    "OHI",
    "OII",
    "OKE",
    "OKLO",
    "OLN",
    "OMC",
    "OMF",
    "ON",
    "ONON",
    "ONTO",
    "OR",
    "ORA",
    "ORCL",
    "ORI",
    "ORLY",
    "OSCR",
    "OTIS",
    "OUT",
    "OWL",
    "OXY",
    "PAAS",
    "PAC",
    "PAM",
    "PANW",
    "PATH",
    "PAY",
    "PAYC",
    "PAYX",
    "PB",
    "PBH",
    "PCAR",
    "PCG",
    "PEN",
    "PEP",
    "PFG",
    "PFS",
    "PFSI",
    "PG",
    "PGR",
    "PH",
    "PHI",
    "PHIN",
    "PII",
    "PINS",
    "PIPR",
    "PL",
    "PLD",
    "PLNT",
    "PLTR",
    "PM",
    "PNC",
    "PNW",
    "PODD",
    "POOL",
    "POR",
    "POST",
    "PPG",
    "PPL",
    "PR",
    "PRGO",
    "PRI",
    "PRIM",
    "PRKS",
    "PRM",
    "PRMB",
    "PRU",
    "PSA",
    "PSKY",
    "PSN",
    "PSO",
    "PSTG",
    "PTC",
    "PUK",
    "PVH",
    "PYPL",
    "QBTS",
    "QCOM",
    "QS",
    "QSR",
    "QTWO",
    "QXO",
    "R",
    "RACE",
    "RBA",
    "RBC",
    "RBLX",
    "RBRK",
    "RCI",
    "RCL",
    "RDDT",
    "RDN",
    "REG",
    "REGN",
    "RELX",
    "REVG",
    "REXR",
    "REZI",
    "RF",
    "RGA",
    "RH",
    "RHI",
    "RHP",
    "RIG",
    "RIO",
    "RKT",
    "RL",
    "RLI",
    "RMD",
    "RNG",
    "RNR",
    "ROK",
    "ROL",
    "ROP",
    "ROST",
    "RPM",
    "RRC",
    "RS",
    "RSG",
    "RSI",
    "RTO",
    "RTX",
    "RXO",
    "RY",
    "RYAN",
    "S",
    "SA",
    "SAH",
    "SAM",
    "SAN",
    "SAP",
    "SARO",
    "SBAC",
    "SBS",
    "SBSW",
    "SCCO",
    "SE",
    "SEE",
    "SEI",
    "SF",
    "SFBS",
    "SGI",
    "SHAK",
    "SHG",
    "SHW",
    "SID",
    "SIG",
    "SII",
    "SJM",
    "SKE",
    "SKM",
    "SKT",
    "SKY",
    "SLB",
    "SLF",
    "SLG",
    "SLGN",
    "SM",
    "SMCI",
    "SMFG",
    "SMR",
    "SN",
    "SNA",
    "SNAP",
    "SNDR",
    "SNPS",
    "SNV",
    "SO",
    "SOLV",
    "SON",
    "SONY",
    "SPG",
    "SPGI",
    "SPHR",
    "SPNT",
    "SPOT",
    "SPXC",
    "SQM",
    "SR",
    "SRE",
    "SSB",
    "SSL",
    "ST",
    "STLA",
    "STLD",
    "STM",
    "STN",
    "STT",
    "STVN",
    "STWD",
    "STX",
    "STZ",
    "SU",
    "SUN",
    "SVV",
    "SW",
    "SWKS",
    "SWX",
    "SXI",
    "SYF",
    "SYK",
    "T",
    "TAK",
    "TAP",
    "TBBB",
    "TD",
    "TDC",
    "TDG",
    "TDY",
    "TECK",
    "TEF",
    "TEL",
    "TEO",
    "TER",
    "TEVA",
    "TEX",
    "TFC",
    "TFII",
    "TFPM",
    "TFX",
    "TGLS",
    "TGNA",
    "TGS",
    "TGT",
    "THC",
    "THG",
    "THO",
    "TIC",
    "TJX",
    "TKO",
    "TKR",
    "TLK",
    "TM",
    "TME",
    "TMO",
    "TMUS",
    "TNET",
    "TNL",
    "TOL",
    "TOST",
    "TPC",
    "TPL",
    "TPR",
    "TREX",
    "TRGP",
    "TRN",
    "TRNO",
    "TRP",
    "TRU",
    "TRV",
    "TS",
    "TSLA",
    "TSLX",
    "TSM",
    "TSN",
    "TT",
    "TTAM",
    "TTC",
    "TTD",
    "TTE",
    "TU",
    "TV",
    "TWLO",
    "TX",
    "TXN",
    "TXT",
    "TYL",
    "U",
    "UAA",
    "UAL",
    "UBER",
    "UBS",
    "UCB",
    "UDR",
    "UGI",
    "UHAL",
    "UHS",
    "UL",
    "ULS",
    "ULTA",
    "UMC",
    "UNF",
    "UNFI",
    "UNH",
    "UNM",
    "UNP",
    "UPS",
    "URI",
    "USB",
    "UWMC",
    "V",
    "VAC",
    "VALE",
    "VEEV",
    "VFC",
    "VG",
    "VICI",
    "VIK",
    "VIPS",
    "VIRT",
    "VLO",
    "VMI",
    "VNO",
    "VOYA",
    "VRNS",
    "VRSK",
    "VRSN",
    "VRTX",
    "VSCO",
    "VSH",
    "VST",
    "VTMX",
    "VTR",
    "VTRS",
    "VVV",
    "VZ",
    "W",
    "WAB",
    "WAL",
    "WAT",
    "WBD",
    "WBS",
    "WCC",
    "WCN",
    "WD",
    "WDAY",
    "WDC",
    "WELL",
    "WF",
    "WFC",
    "WFG",
    "WH",
    "WHD",
    "WHR",
    "WIT",
    "WK",
    "WLK",
    "WLYB",
    "WM",
    "WMS",
    "WMT",
    "WOR",
    "WPM",
    "WPP",
    "WRB",
    "WRBY",
    "WSO",
    "WST",
    "WTM",
    "WTRG",
    "WTS",
    "WU",
    "WWW",
    "WY",
    "WYNN",
    "XOM",
    "XPEV",
    "XPO",
    "XYZ",
    "YELP",
    "YETI",
    "YMM",
    "YOU",
    "YPF",
    "YUM",
    "YUMC",
    "ZBH",
    "ZBRA",
    "ZGN",
    "ZK",
    "ZTO",
    "ZTS",
    "ZWS"
  ],
  "summary": {
    "hot_stocks_count": 175,
    "watch_list_count": 119,
    "failed_count": 0,
    "filtered_by_sma_count": 1111,
    "total_analyzed": 1405
  }
}