{
  "timestamp": "2025-11-27T06:09:45.086309",
  "hot_stocks": [
    {
      "symbol": "APOS",
      "last_close": 26.42,
      "sma150": 26.42,
      "distance_percent": 0.01,
      "atr": 0.14,
      "atr_percent": 0.53,
      "last_volume": 20600,
      "avg_volume_14d": 26414
    },
    {
      "symbol": "RWTN",
      "last_close": 24.75,
      "sma150": 24.75,
      "distance_percent": 0.01,
      "atr": 0.23,
      "atr_percent": 0.92,
      "last_volume": 8700,
      "avg_volume_14d": 7900
    },
    {
      "symbol": "MTCH",
      "last_close": 33.22,
      "sma150": 33.21,
      "distance_percent": 0.02,
      "atr": 0.64,
      "atr_percent": 1.96,
      "last_volume": 2999500,
      "avg_volume_14d": 3475442
    },
    {
      "symbol": "SREA",
      "last_close": 22.06,
      "sma150": 22.05,
      "distance_percent": 0.04,
      "atr": 0.31,
      "atr_percent": 1.39,
      "last_volume": 46700,
      "avg_volume_14d": 43478
    },
    {
      "symbol": "MSCI",
      "last_close": 562.74,
      "sma150": 562.4,
      "distance_percent": 0.06,
      "atr": 10.23,
      "atr_percent": 1.8,
      "last_volume": 575100,
      "avg_volume_14d": 592207
    },
    {
      "symbol": "PK",
      "last_close": 10.83,
      "sma150": 10.82,
      "distance_percent": 0.06,
      "atr": 0.34,
      "atr_percent": 3.27,
      "last_volume": 2025300,
      "avg_volume_14d": 3288235
    },
    {
      "symbol": "ADSK",
      "last_close": 301.38,
      "sma150": 300.99,
      "distance_percent": 0.13,
      "atr": 7.3,
      "atr_percent": 2.47,
      "last_volume": 4685200,
      "avg_volume_14d": 1388007
    },
    {
      "symbol": "APLE",
      "last_close": 11.98,
      "sma150": 11.96,
      "distance_percent": 0.13,
      "atr": 0.26,
      "atr_percent": 2.21,
      "last_volume": 3899600,
      "avg_volume_14d": 2709785
    },
    {
      "symbol": "RHP",
      "last_close": 95.51,
      "sma150": 95.37,
      "distance_percent": 0.14,
      "atr": 2.28,
      "atr_percent": 2.44,
      "last_volume": 587800,
      "avg_volume_14d": 554978
    },
    {
      "symbol": "INFY",
      "last_close": 17.42,
      "sma150": 17.39,
      "distance_percent": 0.18,
      "atr": 0.28,
      "atr_percent": 1.66,
      "last_volume": 8260000,
      "avg_volume_14d": 11078221
    },
    {
      "symbol": "GPC",
      "last_close": 129.86,
      "sma150": 129.57,
      "distance_percent": 0.22,
      "atr": 2.4,
      "atr_percent": 1.89,
      "last_volume": 1103600,
      "avg_volume_14d": 1165828
    },
    {
      "symbol": "BOH",
      "last_close": 66.4,
      "sma150": 66.25,
      "distance_percent": 0.23,
      "atr": 1.42,
      "atr_percent": 2.18,
      "last_volume": 567700,
      "avg_volume_14d": 345685
    },
    {
      "symbol": "ES",
      "last_close": 66.7,
      "sma150": 66.53,
      "distance_percent": 0.26,
      "atr": 1.55,
      "atr_percent": 2.22,
      "last_volume": 1544000,
      "avg_volume_14d": 3488678
    },
    {
      "symbol": "EDU",
      "last_close": 50.86,
      "sma150": 50.72,
      "distance_percent": 0.28,
      "atr": 1.2,
      "atr_percent": 2.25,
      "last_volume": 853600,
      "avg_volume_14d": 954250
    },
    {
      "symbol": "PBA",
      "last_close": 38.08,
      "sma150": 37.97,
      "distance_percent": 0.3,
      "atr": 0.68,
      "atr_percent": 1.78,
      "last_volume": 1456500,
      "avg_volume_14d": 1773657
    },
    {
      "symbol": "PMTU",
      "last_close": 25.53,
      "sma150": 25.46,
      "distance_percent": 0.3,
      "atr": 0.07,
      "atr_percent": 0.29,
      "last_volume": 1900,
      "avg_volume_14d": 2214
    },
    {
      "symbol": "NTAP",
      "last_close": 109.25,
      "sma150": 108.9,
      "distance_percent": 0.32,
      "atr": 3.76,
      "atr_percent": 3.45,
      "last_volume": 5035700,
      "avg_volume_14d": 2346907
    },
    {
      "symbol": "AR",
      "last_close": 35.12,
      "sma150": 34.99,
      "distance_percent": 0.38,
      "atr": 1.39,
      "atr_percent": 4.07,
      "last_volume": 4698300,
      "avg_volume_14d": 5090271
    },
    {
      "symbol": "CBU",
      "last_close": 57.32,
      "sma150": 57.07,
      "distance_percent": 0.44,
      "atr": 1.56,
      "atr_percent": 2.78,
      "last_volume": 352200,
      "avg_volume_14d": 216950
    },
    {
      "symbol": "AQNB",
      "last_close": 25.7,
      "sma150": 25.59,
      "distance_percent": 0.45,
      "atr": 0.11,
      "atr_percent": 0.44,
      "last_volume": 13600,
      "avg_volume_14d": 7214
    },
    {
      "symbol": "WTW",
      "last_close": 321.23,
      "sma150": 319.68,
      "distance_percent": 0.49,
      "atr": 5.5,
      "atr_percent": 1.72,
      "last_volume": 527800,
      "avg_volume_14d": 700535
    },
    {
      "symbol": "BEPH",
      "last_close": 15.58,
      "sma150": 15.5,
      "distance_percent": 0.53,
      "atr": 0.23,
      "atr_percent": 1.45,
      "last_volume": 16600,
      "avg_volume_14d": 29335
    },
    {
      "symbol": "CMSD",
      "last_close": 23.47,
      "sma150": 23.34,
      "distance_percent": 0.56,
      "atr": 0.25,
      "atr_percent": 1.06,
      "last_volume": 38500,
      "avg_volume_14d": 30607
    },
    {
      "symbol": "ECCF",
      "last_close": 25.25,
      "sma150": 25.11,
      "distance_percent": 0.56,
      "atr": 0.11,
      "atr_percent": 0.42,
      "last_volume": 3500,
      "avg_volume_14d": 2335
    },
    {
      "symbol": "LAD",
      "last_close": 318.59,
      "sma150": 316.6,
      "distance_percent": 0.63,
      "atr": 9.15,
      "atr_percent": 3.06,
      "last_volume": 172200,
      "avg_volume_14d": 303357
    },
    {
      "symbol": "HCXY",
      "last_close": 25.3,
      "sma150": 25.14,
      "distance_percent": 0.65,
      "atr": 0.09,
      "atr_percent": 0.35,
      "last_volume": 1000,
      "avg_volume_14d": 614
    },
    {
      "symbol": "RWTO",
      "last_close": 24.7,
      "sma150": 24.54,
      "distance_percent": 0.65,
      "atr": 0.22,
      "atr_percent": 0.88,
      "last_volume": 4400,
      "avg_volume_14d": 6907
    },
    {
      "symbol": "FUL",
      "last_close": 58.67,
      "sma150": 58.29,
      "distance_percent": 0.65,
      "atr": 1.46,
      "atr_percent": 2.54,
      "last_volume": 571000,
      "avg_volume_14d": 383528
    },
    {
      "symbol": "ELC",
      "last_close": 21.08,
      "sma150": 20.94,
      "distance_percent": 0.69,
      "atr": 0.15,
      "atr_percent": 0.7,
      "last_volume": 23400,
      "avg_volume_14d": 23164
    },
    {
      "symbol": "MTB",
      "last_close": 190.24,
      "sma150": 188.88,
      "distance_percent": 0.72,
      "atr": 3.9,
      "atr_percent": 2.09,
      "last_volume": 649900,
      "avg_volume_14d": 899478
    },
    {
      "symbol": "PFGC",
      "last_close": 96.13,
      "sma150": 95.43,
      "distance_percent": 0.73,
      "atr": 2.53,
      "atr_percent": 2.64,
      "last_volume": 1047500,
      "avg_volume_14d": 1430771
    },
    {
      "symbol": "BHC",
      "last_close": 6.25,
      "sma150": 6.2,
      "distance_percent": 0.73,
      "atr": 0.26,
      "atr_percent": 4.02,
      "last_volume": 2065100,
      "avg_volume_14d": 2692092
    },
    {
      "symbol": "RCC",
      "last_close": 24.85,
      "sma150": 24.67,
      "distance_percent": 0.74,
      "atr": 0.06,
      "atr_percent": 0.24,
      "last_volume": 1900,
      "avg_volume_14d": 3621
    },
    {
      "symbol": "SOBO",
      "last_close": 26.94,
      "sma150": 26.73,
      "distance_percent": 0.8,
      "atr": 0.54,
      "atr_percent": 2.01,
      "last_volume": 617800,
      "avg_volume_14d": 884592
    },
    {
      "symbol": "PB",
      "last_close": 68.84,
      "sma150": 68.19,
      "distance_percent": 0.95,
      "atr": 1.43,
      "atr_percent": 2.12,
      "last_volume": 836600,
      "avg_volume_14d": 895335
    },
    {
      "symbol": "ENJ",
      "last_close": 21.42,
      "sma150": 21.22,
      "distance_percent": 0.96,
      "atr": 0.23,
      "atr_percent": 1.05,
      "last_volume": 5800,
      "avg_volume_14d": 1928
    },
    {
      "symbol": "FGN",
      "last_close": 26.54,
      "sma150": 26.28,
      "distance_percent": 0.99,
      "atr": 0.33,
      "atr_percent": 1.26,
      "last_volume": 10200,
      "avg_volume_14d": 10892
    },
    {
      "symbol": "WES",
      "last_close": 39.0,
      "sma150": 38.61,
      "distance_percent": 1.02,
      "atr": 0.71,
      "atr_percent": 1.82,
      "last_volume": 1289800,
      "avg_volume_14d": 1584407
    },
    {
      "symbol": "GATX",
      "last_close": 160.32,
      "sma150": 158.7,
      "distance_percent": 1.02,
      "atr": 3.68,
      "atr_percent": 2.36,
      "last_volume": 179400,
      "avg_volume_14d": 173792
    },
    {
      "symbol": "TROW",
      "last_close": 102.09,
      "sma150": 101.03,
      "distance_percent": 1.05,
      "atr": 2.1,
      "atr_percent": 2.08,
      "last_volume": 1401000,
      "avg_volume_14d": 1691742
    },
    {
      "symbol": "PEG",
      "last_close": 83.25,
      "sma150": 82.38,
      "distance_percent": 1.05,
      "atr": 1.36,
      "atr_percent": 1.65,
      "last_volume": 1529200,
      "avg_volume_14d": 2564764
    },
    {
      "symbol": "EMR",
      "last_close": 131.44,
      "sma150": 130.06,
      "distance_percent": 1.06,
      "atr": 3.49,
      "atr_percent": 2.71,
      "last_volume": 1484000,
      "avg_volume_14d": 2763000
    },
    {
      "symbol": "IEX",
      "last_close": 173.76,
      "sma150": 171.89,
      "distance_percent": 1.09,
      "atr": 3.41,
      "atr_percent": 2.04,
      "last_volume": 406200,
      "avg_volume_14d": 640071
    },
    {
      "symbol": "CMSC",
      "last_close": 23.39,
      "sma150": 23.11,
      "distance_percent": 1.22,
      "atr": 0.18,
      "atr_percent": 0.76,
      "last_volume": 14700,
      "avg_volume_14d": 11907
    },
    {
      "symbol": "WMB",
      "last_close": 60.22,
      "sma150": 59.47,
      "distance_percent": 1.26,
      "atr": 1.42,
      "atr_percent": 2.37,
      "last_volume": 5095600,
      "avg_volume_14d": 7641392
    },
    {
      "symbol": "MGM",
      "last_close": 34.78,
      "sma150": 34.35,
      "distance_percent": 1.26,
      "atr": 1.08,
      "atr_percent": 3.31,
      "last_volume": 4340700,
      "avg_volume_14d": 4938892
    },
    {
      "symbol": "ENO",
      "last_close": 22.78,
      "sma150": 22.49,
      "distance_percent": 1.27,
      "atr": 0.33,
      "atr_percent": 1.45,
      "last_volume": 3800,
      "avg_volume_14d": 4485
    },
    {
      "symbol": "FSS",
      "last_close": 112.79,
      "sma150": 111.35,
      "distance_percent": 1.29,
      "atr": 3.27,
      "atr_percent": 2.98,
      "last_volume": 608900,
      "avg_volume_14d": 316564
    },
    {
      "symbol": "JEF",
      "last_close": 57.23,
      "sma150": 56.48,
      "distance_percent": 1.33,
      "atr": 2.3,
      "atr_percent": 4.15,
      "last_volume": 1364000,
      "avg_volume_14d": 1910492
    },
    {
      "symbol": "SNN",
      "last_close": 33.41,
      "sma150": 32.97,
      "distance_percent": 1.34,
      "atr": 0.45,
      "atr_percent": 1.37,
      "last_volume": 324500,
      "avg_volume_14d": 611250
    },
    {
      "symbol": "FCX",
      "last_close": 42.15,
      "sma150": 41.59,
      "distance_percent": 1.35,
      "atr": 1.34,
      "atr_percent": 3.31,
      "last_volume": 13336400,
      "avg_volume_14d": 15942657
    },
    {
      "symbol": "NET",
      "last_close": 196.99,
      "sma150": 194.28,
      "distance_percent": 1.39,
      "atr": 10.04,
      "atr_percent": 4.82,
      "last_volume": 2255900,
      "avg_volume_14d": 3637214
    },
    {
      "symbol": "ATKR",
      "last_close": 66.89,
      "sma150": 65.97,
      "distance_percent": 1.4,
      "atr": 3.09,
      "atr_percent": 4.8,
      "last_volume": 431800,
      "avg_volume_14d": 663942
    },
    {
      "symbol": "CMSA",
      "last_close": 22.7,
      "sma150": 22.38,
      "distance_percent": 1.42,
      "atr": 0.28,
      "atr_percent": 1.2,
      "last_volume": 7000,
      "avg_volume_14d": 9728
    },
    {
      "symbol": "PAY",
      "last_close": 34.2,
      "sma150": 33.71,
      "distance_percent": 1.47,
      "atr": 1.38,
      "atr_percent": 3.87,
      "last_volume": 436400,
      "avg_volume_14d": 733142
    },
    {
      "symbol": "BBT",
      "last_close": 25.6,
      "sma150": 25.23,
      "distance_percent": 1.48,
      "atr": 0.72,
      "atr_percent": 2.87,
      "last_volume": 867900,
      "avg_volume_14d": 1009807
    },
    {
      "symbol": "PKG",
      "last_close": 203.49,
      "sma150": 200.51,
      "distance_percent": 1.49,
      "atr": 3.79,
      "atr_percent": 1.91,
      "last_volume": 498900,
      "avg_volume_14d": 745092
    },
    {
      "symbol": "GFF",
      "last_close": 75.17,
      "sma150": 74.06,
      "distance_percent": 1.5,
      "atr": 2.72,
      "atr_percent": 3.84,
      "last_volume": 502500,
      "avg_volume_14d": 409992
    },
    {
      "symbol": "WHD",
      "last_close": 42.33,
      "sma150": 41.7,
      "distance_percent": 1.51,
      "atr": 1.78,
      "atr_percent": 4.27,
      "last_volume": 773900,
      "avg_volume_14d": 599107
    },
    {
      "symbol": "WAL",
      "last_close": 81.1,
      "sma150": 79.89,
      "distance_percent": 1.52,
      "atr": 2.48,
      "atr_percent": 3.17,
      "last_volume": 816000,
      "avg_volume_14d": 838457
    },
    {
      "symbol": "BEPI",
      "last_close": 16.45,
      "sma150": 16.21,
      "distance_percent": 1.52,
      "atr": 0.24,
      "atr_percent": 1.48,
      "last_volume": 9000,
      "avg_volume_14d": 10735
    },
    {
      "symbol": "IVT",
      "last_close": 28.54,
      "sma150": 28.11,
      "distance_percent": 1.54,
      "atr": 0.58,
      "atr_percent": 2.06,
      "last_volume": 585700,
      "avg_volume_14d": 585671
    },
    {
      "symbol": "BNH",
      "last_close": 16.3,
      "sma150": 16.05,
      "distance_percent": 1.57,
      "atr": 0.27,
      "atr_percent": 1.65,
      "last_volume": 15600,
      "avg_volume_14d": 24085
    },
    {
      "symbol": "KGS",
      "last_close": 34.93,
      "sma150": 34.39,
      "distance_percent": 1.58,
      "atr": 1.17,
      "atr_percent": 3.45,
      "last_volume": 1404900,
      "avg_volume_14d": 1690085
    },
    {
      "symbol": "OGE",
      "last_close": 45.5,
      "sma150": 44.79,
      "distance_percent": 1.59,
      "atr": 0.74,
      "atr_percent": 1.65,
      "last_volume": 1700000,
      "avg_volume_14d": 1524807
    },
    {
      "symbol": "R",
      "last_close": 172.49,
      "sma150": 169.75,
      "distance_percent": 1.62,
      "atr": 4.33,
      "atr_percent": 2.56,
      "last_volume": 284200,
      "avg_volume_14d": 348692
    },
    {
      "symbol": "LAZ",
      "last_close": 50.42,
      "sma150": 49.61,
      "distance_percent": 1.62,
      "atr": 1.61,
      "atr_percent": 3.27,
      "last_volume": 808800,
      "avg_volume_14d": 818442
    },
    {
      "symbol": "TMHC",
      "last_close": 63.37,
      "sma150": 62.32,
      "distance_percent": 1.69,
      "atr": 1.66,
      "atr_percent": 2.77,
      "last_volume": 785100,
      "avg_volume_14d": 918764
    },
    {
      "symbol": "CALX",
      "last_close": 55.8,
      "sma150": 54.87,
      "distance_percent": 1.69,
      "atr": 2.16,
      "atr_percent": 3.71,
      "last_volume": 950900,
      "avg_volume_14d": 759985
    },
    {
      "symbol": "UCB",
      "last_close": 30.93,
      "sma150": 30.41,
      "distance_percent": 1.71,
      "atr": 0.76,
      "atr_percent": 2.52,
      "last_volume": 1115600,
      "avg_volume_14d": 677278
    },
    {
      "symbol": "BIPH",
      "last_close": 17.08,
      "sma150": 16.79,
      "distance_percent": 1.75,
      "atr": 0.31,
      "atr_percent": 1.81,
      "last_volume": 13700,
      "avg_volume_14d": 12450
    },
    {
      "symbol": "PNR",
      "last_close": 106.08,
      "sma150": 104.24,
      "distance_percent": 1.76,
      "atr": 2.32,
      "atr_percent": 2.21,
      "last_volume": 1080400,
      "avg_volume_14d": 1247271
    },
    {
      "symbol": "DUKB",
      "last_close": 25.0,
      "sma150": 24.55,
      "distance_percent": 1.83,
      "atr": 0.2,
      "atr_percent": 0.78,
      "last_volume": 40400,
      "avg_volume_14d": 33242
    },
    {
      "symbol": "NDAQ",
      "last_close": 89.98,
      "sma150": 88.35,
      "distance_percent": 1.85,
      "atr": 1.47,
      "atr_percent": 1.68,
      "last_volume": 1785400,
      "avg_volume_14d": 2553214
    },
    {
      "symbol": "DUK",
      "last_close": 123.43,
      "sma150": 121.1,
      "distance_percent": 1.92,
      "atr": 1.85,
      "atr_percent": 1.5,
      "last_volume": 3374400,
      "avg_volume_14d": 3747092
    },
    {
      "symbol": "GJS",
      "last_close": 23.29,
      "sma150": 22.85,
      "distance_percent": 1.93,
      "atr": 0.06,
      "atr_percent": 0.25,
      "last_volume": 6800,
      "avg_volume_14d": 800
    },
    {
      "symbol": "LH",
      "last_close": 268.27,
      "sma150": 263.16,
      "distance_percent": 1.94,
      "atr": 6.29,
      "atr_percent": 2.38,
      "last_volume": 605100,
      "avg_volume_14d": 1108864
    },
    {
      "symbol": "HPE",
      "last_close": 21.53,
      "sma150": 21.11,
      "distance_percent": 1.97,
      "atr": 0.85,
      "atr_percent": 3.87,
      "last_volume": 19603600,
      "avg_volume_14d": 31521564
    },
    {
      "symbol": "LOW",
      "last_close": 241.61,
      "sma150": 236.9,
      "distance_percent": 1.99,
      "atr": 5.46,
      "atr_percent": 2.36,
      "last_volume": 2303300,
      "avg_volume_14d": 4005278
    },
    {
      "symbol": "TTWO",
      "last_close": 243.63,
      "sma150": 238.8,
      "distance_percent": 2.02,
      "atr": 6.59,
      "atr_percent": 2.77,
      "last_volume": 1026800,
      "avg_volume_14d": 2210228
    },
    {
      "symbol": "FRT",
      "last_close": 98.57,
      "sma150": 96.6,
      "distance_percent": 2.04,
      "atr": 1.58,
      "atr_percent": 1.63,
      "last_volume": 548700,
      "avg_volume_14d": 644157
    },
    {
      "symbol": "AZO",
      "last_close": 3967.95,
      "sma150": 3888.15,
      "distance_percent": 2.05,
      "atr": 71.15,
      "atr_percent": 1.86,
      "last_volume": 67900,
      "avg_volume_14d": 115514
    },
    {
      "symbol": "NAN",
      "last_close": 11.55,
      "sma150": 11.32,
      "distance_percent": 2.07,
      "atr": 0.07,
      "atr_percent": 0.63,
      "last_volume": 75700,
      "avg_volume_14d": 69328
    },
    {
      "symbol": "AX",
      "last_close": 81.99,
      "sma150": 80.3,
      "distance_percent": 2.1,
      "atr": 2.42,
      "atr_percent": 3.04,
      "last_volume": 365800,
      "avg_volume_14d": 281185
    },
    {
      "symbol": "XPEV",
      "last_close": 21.14,
      "sma150": 20.67,
      "distance_percent": 2.28,
      "atr": 1.33,
      "atr_percent": 5.72,
      "last_volume": 9458500,
      "avg_volume_14d": 23785592
    },
    {
      "symbol": "BNL",
      "last_close": 17.55,
      "sma150": 17.16,
      "distance_percent": 2.29,
      "atr": 0.37,
      "atr_percent": 2.06,
      "last_volume": 4711900,
      "avg_volume_14d": 1699700
    },
    {
      "symbol": "BXMT",
      "last_close": 19.46,
      "sma150": 19.02,
      "distance_percent": 2.34,
      "atr": 0.36,
      "atr_percent": 1.93,
      "last_volume": 2298200,
      "avg_volume_14d": 1086914
    },
    {
      "symbol": "HEI",
      "last_close": 315.26,
      "sma150": 307.95,
      "distance_percent": 2.37,
      "atr": 8.14,
      "atr_percent": 2.58,
      "last_volume": 261800,
      "avg_volume_14d": 391300
    },
    {
      "symbol": "CNR",
      "last_close": 78.36,
      "sma150": 76.54,
      "distance_percent": 2.38,
      "atr": 3.77,
      "atr_percent": 4.62,
      "last_volume": 1062400,
      "avg_volume_14d": 926614
    },
    {
      "symbol": "SUI",
      "last_close": 128.58,
      "sma150": 125.56,
      "distance_percent": 2.41,
      "atr": 1.95,
      "atr_percent": 1.54,
      "last_volume": 548900,
      "avg_volume_14d": 518092
    },
    {
      "symbol": "PNC",
      "last_close": 191.88,
      "sma150": 187.35,
      "distance_percent": 2.42,
      "atr": 3.81,
      "atr_percent": 2.05,
      "last_volume": 1516400,
      "avg_volume_14d": 1937178
    },
    {
      "symbol": "ENB",
      "last_close": 48.04,
      "sma150": 46.9,
      "distance_percent": 2.44,
      "atr": 0.87,
      "atr_percent": 1.82,
      "last_volume": 2824200,
      "avg_volume_14d": 5426514
    },
    {
      "symbol": "MAC",
      "last_close": 17.24,
      "sma150": 16.82,
      "distance_percent": 2.47,
      "atr": 0.55,
      "atr_percent": 3.21,
      "last_volume": 2419400,
      "avg_volume_14d": 1659621
    },
    {
      "symbol": "SLB",
      "last_close": 35.66,
      "sma150": 34.79,
      "distance_percent": 2.5,
      "atr": 1.13,
      "atr_percent": 3.13,
      "last_volume": 9752900,
      "avg_volume_14d": 14249921
    },
    {
      "symbol": "PPL",
      "last_close": 36.71,
      "sma150": 35.8,
      "distance_percent": 2.54,
      "atr": 0.52,
      "atr_percent": 1.42,
      "last_volume": 5127100,
      "avg_volume_14d": 7499871
    },
    {
      "symbol": "TAL",
      "last_close": 11.06,
      "sma150": 10.79,
      "distance_percent": 2.55,
      "atr": 0.32,
      "atr_percent": 2.82,
      "last_volume": 2465200,
      "avg_volume_14d": 3461335
    },
    {
      "symbol": "HUBB",
      "last_close": 428.47,
      "sma150": 417.64,
      "distance_percent": 2.59,
      "atr": 12.64,
      "atr_percent": 2.92,
      "last_volume": 324802,
      "avg_volume_14d": 524208
    },
    {
      "symbol": "ASH",
      "last_close": 52.54,
      "sma150": 51.17,
      "distance_percent": 2.67,
      "atr": 1.66,
      "atr_percent": 3.28,
      "last_volume": 863700,
      "avg_volume_14d": 944935
    },
    {
      "symbol": "JBL",
      "last_close": 207.23,
      "sma150": 201.64,
      "distance_percent": 2.77,
      "atr": 8.14,
      "atr_percent": 3.99,
      "last_volume": 877300,
      "avg_volume_14d": 1170300
    },
    {
      "symbol": "USFD",
      "last_close": 78.69,
      "sma150": 76.56,
      "distance_percent": 2.78,
      "atr": 1.77,
      "atr_percent": 2.43,
      "last_volume": 1871300,
      "avg_volume_14d": 2370978
    },
    {
      "symbol": "MATX",
      "last_close": 109.14,
      "sma150": 106.19,
      "distance_percent": 2.78,
      "atr": 3.56,
      "atr_percent": 3.33,
      "last_volume": 348700,
      "avg_volume_14d": 365114
    },
    {
      "symbol": "RRX",
      "last_close": 145.65,
      "sma150": 141.69,
      "distance_percent": 2.8,
      "atr": 5.89,
      "atr_percent": 4.33,
      "last_volume": 817300,
      "avg_volume_14d": 912542
    },
    {
      "symbol": "UNP",
      "last_close": 230.66,
      "sma150": 224.38,
      "distance_percent": 2.8,
      "atr": 3.3,
      "atr_percent": 1.48,
      "last_volume": 3233700,
      "avg_volume_14d": 3304992
    },
    {
      "symbol": "WEC",
      "last_close": 112.24,
      "sma150": 109.13,
      "distance_percent": 2.85,
      "atr": 1.31,
      "atr_percent": 1.18,
      "last_volume": 1324900,
      "avg_volume_14d": 2130142
    },
    {
      "symbol": "TR",
      "last_close": 38.71,
      "sma150": 37.63,
      "distance_percent": 2.88,
      "atr": 1.13,
      "atr_percent": 2.9,
      "last_volume": 183000,
      "avg_volume_14d": 144514
    },
    {
      "symbol": "CME",
      "last_close": 280.87,
      "sma150": 272.95,
      "distance_percent": 2.9,
      "atr": 5.81,
      "atr_percent": 2.09,
      "last_volume": 1439700,
      "avg_volume_14d": 2195907
    },
    {
      "symbol": "SHEL",
      "last_close": 73.41,
      "sma150": 71.33,
      "distance_percent": 2.91,
      "atr": 0.94,
      "atr_percent": 1.26,
      "last_volume": 3363030,
      "avg_volume_14d": 4483399
    },
    {
      "symbol": "AIT",
      "last_close": 257.32,
      "sma150": 250.01,
      "distance_percent": 2.93,
      "atr": 6.62,
      "atr_percent": 2.64,
      "last_volume": 241200,
      "avg_volume_14d": 254007
    },
    {
      "symbol": "ECL",
      "last_close": 274.99,
      "sma150": 267.13,
      "distance_percent": 2.94,
      "atr": 4.59,
      "atr_percent": 1.75,
      "last_volume": 1281400,
      "avg_volume_14d": 1515585
    },
    {
      "symbol": "SWK",
      "last_close": 71.83,
      "sma150": 69.75,
      "distance_percent": 2.98,
      "atr": 2.1,
      "atr_percent": 3.15,
      "last_volume": 1706900,
      "avg_volume_14d": 1511392
    },
    {
      "symbol": "ALE",
      "last_close": 67.58,
      "sma150": 65.62,
      "distance_percent": 2.99,
      "atr": 0.13,
      "atr_percent": 0.19,
      "last_volume": 563000,
      "avg_volume_14d": 667885
    },
    {
      "symbol": "PBR",
      "last_close": 12.66,
      "sma150": 12.29,
      "distance_percent": 3.0,
      "atr": 0.31,
      "atr_percent": 2.42,
      "last_volume": 15290400,
      "avg_volume_14d": 20433450
    },
    {
      "symbol": "PAC",
      "last_close": 236.54,
      "sma150": 229.63,
      "distance_percent": 3.01,
      "atr": 5.52,
      "atr_percent": 2.49,
      "last_volume": 84100,
      "avg_volume_14d": 96678
    },
    {
      "symbol": "GL",
      "last_close": 134.87,
      "sma150": 130.91,
      "distance_percent": 3.03,
      "atr": 2.26,
      "atr_percent": 1.7,
      "last_volume": 557800,
      "avg_volume_14d": 493814
    },
    {
      "symbol": "TXNM",
      "last_close": 58.15,
      "sma150": 56.44,
      "distance_percent": 3.03,
      "atr": 0.32,
      "atr_percent": 0.55,
      "last_volume": 763500,
      "avg_volume_14d": 814364
    },
    {
      "symbol": "AB",
      "last_close": 41.1,
      "sma150": 39.87,
      "distance_percent": 3.08,
      "atr": 0.68,
      "atr_percent": 1.72,
      "last_volume": 157700,
      "avg_volume_14d": 182107
    },
    {
      "symbol": "K",
      "last_close": 83.6,
      "sma150": 81.1,
      "distance_percent": 3.08,
      "atr": 0.12,
      "atr_percent": 0.15,
      "last_volume": 2312500,
      "avg_volume_14d": 2492242
    },
    {
      "symbol": "XYL",
      "last_close": 141.12,
      "sma150": 136.85,
      "distance_percent": 3.12,
      "atr": 2.73,
      "atr_percent": 1.9,
      "last_volume": 1442600,
      "avg_volume_14d": 1534407
    },
    {
      "symbol": "KTB",
      "last_close": 74.24,
      "sma150": 71.97,
      "distance_percent": 3.16,
      "atr": 2.09,
      "atr_percent": 2.92,
      "last_volume": 588300,
      "avg_volume_14d": 587842
    },
    {
      "symbol": "PRU",
      "last_close": 107.97,
      "sma150": 104.66,
      "distance_percent": 3.16,
      "atr": 1.94,
      "atr_percent": 1.82,
      "last_volume": 1419400,
      "avg_volume_14d": 1914971
    },
    {
      "symbol": "BEPJ",
      "last_close": 25.3,
      "sma150": 24.52,
      "distance_percent": 3.18,
      "atr": 0.25,
      "atr_percent": 0.99,
      "last_volume": 6100,
      "avg_volume_14d": 6828
    },
    {
      "symbol": "RDN",
      "last_close": 35.54,
      "sma150": 34.44,
      "distance_percent": 3.19,
      "atr": 0.72,
      "atr_percent": 2.06,
      "last_volume": 1392500,
      "avg_volume_14d": 719285
    },
    {
      "symbol": "ALV",
      "last_close": 118.26,
      "sma150": 114.56,
      "distance_percent": 3.23,
      "atr": 2.56,
      "atr_percent": 2.15,
      "last_volume": 606200,
      "avg_volume_14d": 559864
    },
    {
      "symbol": "AZZ",
      "last_close": 105.67,
      "sma150": 102.32,
      "distance_percent": 3.27,
      "atr": 2.91,
      "atr_percent": 2.88,
      "last_volume": 231700,
      "avg_volume_14d": 227135
    },
    {
      "symbol": "NIO",
      "last_close": 5.46,
      "sma150": 5.29,
      "distance_percent": 3.29,
      "atr": 0.32,
      "atr_percent": 5.31,
      "last_volume": 85752200,
      "avg_volume_14d": 59572107
    },
    {
      "symbol": "KRG",
      "last_close": 23.07,
      "sma150": 22.34,
      "distance_percent": 3.29,
      "atr": 0.44,
      "atr_percent": 1.96,
      "last_volume": 1189100,
      "avg_volume_14d": 1608064
    },
    {
      "symbol": "DG",
      "last_close": 108.77,
      "sma150": 105.29,
      "distance_percent": 3.31,
      "atr": 3.08,
      "atr_percent": 3.0,
      "last_volume": 3118400,
      "avg_volume_14d": 3006135
    },
    {
      "symbol": "NOC",
      "last_close": 567.11,
      "sma150": 548.55,
      "distance_percent": 3.38,
      "atr": 9.4,
      "atr_percent": 1.66,
      "last_volume": 445800,
      "avg_volume_14d": 801750
    },
    {
      "symbol": "COF",
      "last_close": 217.47,
      "sma150": 210.28,
      "distance_percent": 3.42,
      "atr": 5.96,
      "atr_percent": 2.82,
      "last_volume": 2431500,
      "avg_volume_14d": 4387792
    },
    {
      "symbol": "LHX",
      "last_close": 276.14,
      "sma150": 266.9,
      "distance_percent": 3.46,
      "atr": 6.14,
      "atr_percent": 2.14,
      "last_volume": 856900,
      "avg_volume_14d": 1285564
    },
    {
      "symbol": "XOM",
      "last_close": 114.77,
      "sma150": 110.92,
      "distance_percent": 3.47,
      "atr": 2.19,
      "atr_percent": 1.86,
      "last_volume": 11643600,
      "avg_volume_14d": 15640978
    },
    {
      "symbol": "RRC",
      "last_close": 38.46,
      "sma150": 37.17,
      "distance_percent": 3.48,
      "atr": 1.25,
      "atr_percent": 3.26,
      "last_volume": 2745900,
      "avg_volume_14d": 2790914
    },
    {
      "symbol": "OVV",
      "last_close": 40.45,
      "sma150": 39.08,
      "distance_percent": 3.52,
      "atr": 1.34,
      "atr_percent": 3.44,
      "last_volume": 3335300,
      "avg_volume_14d": 3782214
    },
    {
      "symbol": "QGEN",
      "last_close": 48.1,
      "sma150": 46.46,
      "distance_percent": 3.52,
      "atr": 0.77,
      "atr_percent": 1.7,
      "last_volume": 1029400,
      "avg_volume_14d": 1210750
    },
    {
      "symbol": "GXO",
      "last_close": 50.5,
      "sma150": 48.78,
      "distance_percent": 3.53,
      "atr": 1.7,
      "atr_percent": 3.45,
      "last_volume": 690400,
      "avg_volume_14d": 1183185
    },
    {
      "symbol": "EE",
      "last_close": 27.55,
      "sma150": 26.61,
      "distance_percent": 3.53,
      "atr": 1.01,
      "atr_percent": 3.73,
      "last_volume": 256300,
      "avg_volume_14d": 480128
    },
    {
      "symbol": "UBS",
      "last_close": 38.05,
      "sma150": 36.75,
      "distance_percent": 3.53,
      "atr": 0.55,
      "atr_percent": 1.45,
      "last_volume": 1192600,
      "avg_volume_14d": 1729042
    },
    {
      "symbol": "APTV",
      "last_close": 76.83,
      "sma150": 74.2,
      "distance_percent": 3.54,
      "atr": 2.32,
      "atr_percent": 2.98,
      "last_volume": 1455900,
      "avg_volume_14d": 2510528
    },
    {
      "symbol": "FITB",
      "last_close": 43.33,
      "sma150": 41.83,
      "distance_percent": 3.58,
      "atr": 0.92,
      "atr_percent": 2.16,
      "last_volume": 4115900,
      "avg_volume_14d": 6675921
    },
    {
      "symbol": "EPD",
      "last_close": 32.53,
      "sma150": 31.39,
      "distance_percent": 3.63,
      "atr": 0.56,
      "atr_percent": 1.74,
      "last_volume": 2826500,
      "avg_volume_14d": 4285471
    },
    {
      "symbol": "BXP",
      "last_close": 72.71,
      "sma150": 70.13,
      "distance_percent": 3.68,
      "atr": 1.56,
      "atr_percent": 2.21,
      "last_volume": 1231300,
      "avg_volume_14d": 1374942
    },
    {
      "symbol": "WPC",
      "last_close": 67.39,
      "sma150": 64.95,
      "distance_percent": 3.76,
      "atr": 0.88,
      "atr_percent": 1.31,
      "last_volume": 1064100,
      "avg_volume_14d": 1263764
    },
    {
      "symbol": "QCOM",
      "last_close": 165.14,
      "sma150": 159.15,
      "distance_percent": 3.76,
      "atr": 5.21,
      "atr_percent": 3.1,
      "last_volume": 7964100,
      "avg_volume_14d": 10270642
    },
    {
      "symbol": "GDV",
      "last_close": 27.14,
      "sma150": 26.14,
      "distance_percent": 3.82,
      "atr": 0.37,
      "atr_percent": 1.39,
      "last_volume": 92200,
      "avg_volume_14d": 123114
    },
    {
      "symbol": "BYD",
      "last_close": 83.38,
      "sma150": 80.31,
      "distance_percent": 3.82,
      "atr": 1.77,
      "atr_percent": 2.2,
      "last_volume": 798300,
      "avg_volume_14d": 845207
    },
    {
      "symbol": "CRGY",
      "last_close": 9.25,
      "sma150": 8.91,
      "distance_percent": 3.83,
      "atr": 0.51,
      "atr_percent": 5.64,
      "last_volume": 4257200,
      "avg_volume_14d": 6361857
    },
    {
      "symbol": "FLG",
      "last_close": 12.17,
      "sma150": 11.72,
      "distance_percent": 3.86,
      "atr": 0.35,
      "atr_percent": 3.16,
      "last_volume": 4396000,
      "avg_volume_14d": 4903742
    },
    {
      "symbol": "MSM",
      "last_close": 89.34,
      "sma150": 86.01,
      "distance_percent": 3.87,
      "atr": 2.34,
      "atr_percent": 2.68,
      "last_volume": 366400,
      "avg_volume_14d": 689871
    },
    {
      "symbol": "AMZN",
      "last_close": 229.16,
      "sma150": 220.43,
      "distance_percent": 3.96,
      "atr": 6.12,
      "atr_percent": 2.63,
      "last_volume": 38435400,
      "avg_volume_14d": 46809128
    },
    {
      "symbol": "AFL",
      "last_close": 110.55,
      "sma150": 106.31,
      "distance_percent": 3.99,
      "atr": 1.7,
      "atr_percent": 1.52,
      "last_volume": 1825300,
      "avg_volume_14d": 2609671
    }
  ],
  "watch_list": [
    {
      "symbol": "MRP",
      "last_close": 30.65,
      "sma150": 30.66,
      "distance_percent": -0.02,
      "atr": 0.99,
      "atr_percent": 3.22,
      "last_volume": 4065700,
      "avg_volume_14d": 4155242
    },
    {
      "symbol": "BCE",
      "last_close": 23.2,
      "sma150": 23.21,
      "distance_percent": -0.04,
      "atr": 0.43,
      "atr_percent": 1.88,
      "last_volume": 2109700,
      "avg_volume_14d": 3337628
    },
    {
      "symbol": "FCN",
      "last_close": 163.95,
      "sma150": 164.08,
      "distance_percent": -0.08,
      "atr": 3.33,
      "atr_percent": 2.03,
      "last_volume": 245700,
      "avg_volume_14d": 260221
    },
    {
      "symbol": "DTE",
      "last_close": 136.78,
      "sma150": 136.9,
      "distance_percent": -0.09,
      "atr": 1.86,
      "atr_percent": 1.35,
      "last_volume": 1048600,
      "avg_volume_14d": 1548835
    },
    {
      "symbol": "REG",
      "last_close": 71.26,
      "sma150": 71.34,
      "distance_percent": -0.11,
      "atr": 1.13,
      "atr_percent": 1.61,
      "last_volume": 1488000,
      "avg_volume_14d": 1088264
    },
    {
      "symbol": "HDB",
      "last_close": 36.63,
      "sma150": 36.69,
      "distance_percent": -0.16,
      "atr": 0.52,
      "atr_percent": 1.43,
      "last_volume": 2228100,
      "avg_volume_14d": 3515764
    },
    {
      "symbol": "WSM",
      "last_close": 181.12,
      "sma150": 181.55,
      "distance_percent": -0.24,
      "atr": 7.06,
      "atr_percent": 3.85,
      "last_volume": 968900,
      "avg_volume_14d": 1502492
    },
    {
      "symbol": "RITM",
      "last_close": 11.52,
      "sma150": 11.55,
      "distance_percent": -0.29,
      "atr": 0.19,
      "atr_percent": 1.69,
      "last_volume": 5101000,
      "avg_volume_14d": 5776557
    },
    {
      "symbol": "NVR",
      "last_close": 7566.67,
      "sma150": 7590.71,
      "distance_percent": -0.32,
      "atr": 133.42,
      "atr_percent": 1.83,
      "last_volume": 15000,
      "avg_volume_14d": 22250
    },
    {
      "symbol": "CR",
      "last_close": 182.78,
      "sma150": 183.37,
      "distance_percent": -0.32,
      "atr": 5.17,
      "atr_percent": 2.82,
      "last_volume": 408100,
      "avg_volume_14d": 316028
    },
    {
      "symbol": "PRS",
      "last_close": 24.01,
      "sma150": 24.09,
      "distance_percent": -0.34,
      "atr": 0.21,
      "atr_percent": 0.89,
      "last_volume": 41600,
      "avg_volume_14d": 34028
    },
    {
      "symbol": "HBAN",
      "last_close": 16.27,
      "sma150": 16.33,
      "distance_percent": -0.37,
      "atr": 0.33,
      "atr_percent": 2.12,
      "last_volume": 33297800,
      "avg_volume_14d": 28003064
    },
    {
      "symbol": "UMC",
      "last_close": 7.33,
      "sma150": 7.36,
      "distance_percent": -0.38,
      "atr": 0.15,
      "atr_percent": 2.09,
      "last_volume": 8086900,
      "avg_volume_14d": 8381607
    },
    {
      "symbol": "AVY",
      "last_close": 172.22,
      "sma150": 172.87,
      "distance_percent": -0.38,
      "atr": 3.48,
      "atr_percent": 2.03,
      "last_volume": 635900,
      "avg_volume_14d": 733028
    },
    {
      "symbol": "SCHW",
      "last_close": 91.8,
      "sma150": 92.18,
      "distance_percent": -0.41,
      "atr": 2.19,
      "atr_percent": 2.35,
      "last_volume": 6697200,
      "avg_volume_14d": 8631028
    },
    {
      "symbol": "MHK",
      "last_close": 115.5,
      "sma150": 115.98,
      "distance_percent": -0.41,
      "atr": 2.79,
      "atr_percent": 2.58,
      "last_volume": 812000,
      "avg_volume_14d": 879707
    },
    {
      "symbol": "CVX",
      "last_close": 149.51,
      "sma150": 150.18,
      "distance_percent": -0.44,
      "atr": 2.63,
      "atr_percent": 1.72,
      "last_volume": 7577800,
      "avg_volume_14d": 9203850
    },
    {
      "symbol": "ON",
      "last_close": 49.64,
      "sma150": 49.86,
      "distance_percent": -0.45,
      "atr": 1.88,
      "atr_percent": 3.96,
      "last_volume": 8294200,
      "avg_volume_14d": 8755814
    },
    {
      "symbol": "ATHS",
      "last_close": 25.19,
      "sma150": 25.31,
      "distance_percent": -0.46,
      "atr": 0.16,
      "atr_percent": 0.62,
      "last_volume": 131700,
      "avg_volume_14d": 36335
    },
    {
      "symbol": "PJT",
      "last_close": 167.98,
      "sma150": 168.78,
      "distance_percent": -0.47,
      "atr": 4.79,
      "atr_percent": 2.89,
      "last_volume": 280800,
      "avg_volume_14d": 235585
    },
    {
      "symbol": "RNG",
      "last_close": 27.92,
      "sma150": 28.06,
      "distance_percent": -0.5,
      "atr": 0.83,
      "atr_percent": 3.06,
      "last_volume": 1027800,
      "avg_volume_14d": 1582842
    },
    {
      "symbol": "MCO",
      "last_close": 487.13,
      "sma150": 489.61,
      "distance_percent": -0.51,
      "atr": 8.41,
      "atr_percent": 1.74,
      "last_volume": 548200,
      "avg_volume_14d": 754385
    },
    {
      "symbol": "CIMN",
      "last_close": 25.01,
      "sma150": 25.15,
      "distance_percent": -0.55,
      "atr": 0.14,
      "atr_percent": 0.57,
      "last_volume": 2400,
      "avg_volume_14d": 13771
    },
    {
      "symbol": "AGCO",
      "last_close": 105.58,
      "sma150": 106.19,
      "distance_percent": -0.58,
      "atr": 3.29,
      "atr_percent": 3.13,
      "last_volume": 1250600,
      "avg_volume_14d": 544850
    },
    {
      "symbol": "HGV",
      "last_close": 42.54,
      "sma150": 42.79,
      "distance_percent": -0.58,
      "atr": 1.32,
      "atr_percent": 3.33,
      "last_volume": 788800,
      "avg_volume_14d": 906800
    },
    {
      "symbol": "BURL",
      "last_close": 260.65,
      "sma150": 262.21,
      "distance_percent": -0.59,
      "atr": 10.45,
      "atr_percent": 3.75,
      "last_volume": 1804400,
      "avg_volume_14d": 1286542
    },
    {
      "symbol": "BNJ",
      "last_close": 15.43,
      "sma150": 15.52,
      "distance_percent": -0.6,
      "atr": 0.21,
      "atr_percent": 1.34,
      "last_volume": 6100,
      "avg_volume_14d": 17085
    },
    {
      "symbol": "UNM",
      "last_close": 76.38,
      "sma150": 76.85,
      "distance_percent": -0.61,
      "atr": 1.56,
      "atr_percent": 2.03,
      "last_volume": 1291200,
      "avg_volume_14d": 1218078
    },
    {
      "symbol": "MFAO",
      "last_close": 25.05,
      "sma150": 25.21,
      "distance_percent": -0.64,
      "atr": 0.11,
      "atr_percent": 0.42,
      "last_volume": 4100,
      "avg_volume_14d": 12678
    },
    {
      "symbol": "MFAN",
      "last_close": 24.91,
      "sma150": 25.07,
      "distance_percent": -0.65,
      "atr": 0.12,
      "atr_percent": 0.49,
      "last_volume": 9800,
      "avg_volume_14d": 22800
    },
    {
      "symbol": "DKS",
      "last_close": 207.41,
      "sma150": 208.78,
      "distance_percent": -0.66,
      "atr": 7.46,
      "atr_percent": 3.51,
      "last_volume": 3154000,
      "avg_volume_14d": 1596271
    },
    {
      "symbol": "SBUX",
      "last_close": 86.7,
      "sma150": 87.28,
      "distance_percent": -0.66,
      "atr": 2.48,
      "atr_percent": 2.92,
      "last_volume": 7602000,
      "avg_volume_14d": 10185071
    },
    {
      "symbol": "DTB",
      "last_close": 17.67,
      "sma150": 17.79,
      "distance_percent": -0.66,
      "atr": 0.19,
      "atr_percent": 1.09,
      "last_volume": 28600,
      "avg_volume_14d": 19778
    },
    {
      "symbol": "UE",
      "last_close": 19.23,
      "sma150": 19.36,
      "distance_percent": -0.69,
      "atr": 0.4,
      "atr_percent": 2.14,
      "last_volume": 1182900,
      "avg_volume_14d": 649878
    },
    {
      "symbol": "HOMB",
      "last_close": 28.18,
      "sma150": 28.38,
      "distance_percent": -0.72,
      "atr": 0.56,
      "atr_percent": 2.05,
      "last_volume": 758400,
      "avg_volume_14d": 899350
    },
    {
      "symbol": "VOYA",
      "last_close": 70.66,
      "sma150": 71.18,
      "distance_percent": -0.73,
      "atr": 1.81,
      "atr_percent": 2.58,
      "last_volume": 674200,
      "avg_volume_14d": 871021
    },
    {
      "symbol": "SCI",
      "last_close": 79.03,
      "sma150": 79.66,
      "distance_percent": -0.79,
      "atr": 1.36,
      "atr_percent": 1.71,
      "last_volume": 648800,
      "avg_volume_14d": 838692
    },
    {
      "symbol": "TT",
      "last_close": 419.64,
      "sma150": 423.0,
      "distance_percent": -0.79,
      "atr": 11.65,
      "atr_percent": 2.8,
      "last_volume": 930600,
      "avg_volume_14d": 1200721
    },
    {
      "symbol": "KAR",
      "last_close": 25.2,
      "sma150": 25.41,
      "distance_percent": -0.82,
      "atr": 0.59,
      "atr_percent": 2.33,
      "last_volume": 1494800,
      "avg_volume_14d": 1013450
    },
    {
      "symbol": "CRC",
      "last_close": 46.9,
      "sma150": 47.35,
      "distance_percent": -0.96,
      "atr": 1.41,
      "atr_percent": 2.98,
      "last_volume": 1212900,
      "avg_volume_14d": 941864
    },
    {
      "symbol": "IR",
      "last_close": 79.87,
      "sma150": 80.67,
      "distance_percent": -0.99,
      "atr": 1.95,
      "atr_percent": 2.55,
      "last_volume": 2230100,
      "avg_volume_14d": 3154664
    },
    {
      "symbol": "MGY",
      "last_close": 22.93,
      "sma150": 23.16,
      "distance_percent": -0.99,
      "atr": 0.67,
      "atr_percent": 2.96,
      "last_volume": 2624200,
      "avg_volume_14d": 2277742
    },
    {
      "symbol": "SNV",
      "last_close": 48.31,
      "sma150": 48.81,
      "distance_percent": -1.02,
      "atr": 1.42,
      "atr_percent": 3.08,
      "last_volume": 977100,
      "avg_volume_14d": 933035
    },
    {
      "symbol": "SSD",
      "last_close": 168.19,
      "sma150": 169.94,
      "distance_percent": -1.03,
      "atr": 4.05,
      "atr_percent": 2.46,
      "last_volume": 280000,
      "avg_volume_14d": 282471
    },
    {
      "symbol": "BRX",
      "last_close": 26.13,
      "sma150": 26.4,
      "distance_percent": -1.03,
      "atr": 0.47,
      "atr_percent": 1.79,
      "last_volume": 3069400,
      "avg_volume_14d": 2324485
    },
    {
      "symbol": "VLTO",
      "last_close": 101.27,
      "sma150": 102.34,
      "distance_percent": -1.04,
      "atr": 1.79,
      "atr_percent": 1.81,
      "last_volume": 1708300,
      "avg_volume_14d": 1974807
    },
    {
      "symbol": "O",
      "last_close": 57.14,
      "sma150": 57.79,
      "distance_percent": -1.12,
      "atr": 0.71,
      "atr_percent": 1.25,
      "last_volume": 5126800,
      "avg_volume_14d": 6269257
    },
    {
      "symbol": "IONQ",
      "last_close": 46.9,
      "sma150": 47.45,
      "distance_percent": -1.15,
      "atr": 4.73,
      "atr_percent": 9.72,
      "last_volume": 12445300,
      "avg_volume_14d": 27617964
    },
    {
      "symbol": "SOJC",
      "last_close": 22.1,
      "sma150": 22.36,
      "distance_percent": -1.15,
      "atr": 0.22,
      "atr_percent": 0.99,
      "last_volume": 29700,
      "avg_volume_14d": 20328
    },
    {
      "symbol": "CLH",
      "last_close": 227.08,
      "sma150": 229.77,
      "distance_percent": -1.17,
      "atr": 5.88,
      "atr_percent": 2.78,
      "last_volume": 590100,
      "avg_volume_14d": 626064
    },
    {
      "symbol": "ABG",
      "last_close": 234.5,
      "sma150": 237.47,
      "distance_percent": -1.25,
      "atr": 7.82,
      "atr_percent": 3.51,
      "last_volume": 245200,
      "avg_volume_14d": 159800
    },
    {
      "symbol": "SOJE",
      "last_close": 17.89,
      "sma150": 18.13,
      "distance_percent": -1.31,
      "atr": 0.2,
      "atr_percent": 1.11,
      "last_volume": 37700,
      "avg_volume_14d": 70342
    },
    {
      "symbol": "ITW",
      "last_close": 248.99,
      "sma150": 252.36,
      "distance_percent": -1.34,
      "atr": 4.14,
      "atr_percent": 1.69,
      "last_volume": 725700,
      "avg_volume_14d": 1167057
    },
    {
      "symbol": "SHW",
      "last_close": 343.39,
      "sma150": 348.05,
      "distance_percent": -1.34,
      "atr": 6.94,
      "atr_percent": 2.06,
      "last_volume": 1174300,
      "avg_volume_14d": 2067307
    },
    {
      "symbol": "PRH",
      "last_close": 24.85,
      "sma150": 25.19,
      "distance_percent": -1.34,
      "atr": 0.2,
      "atr_percent": 0.82,
      "last_volume": 41900,
      "avg_volume_14d": 29100
    },
    {
      "symbol": "BSX",
      "last_close": 100.96,
      "sma150": 102.34,
      "distance_percent": -1.35,
      "atr": 2.19,
      "atr_percent": 2.18,
      "last_volume": 5310100,
      "avg_volume_14d": 9755371
    },
    {
      "symbol": "NTR",
      "last_close": 57.4,
      "sma150": 58.19,
      "distance_percent": -1.35,
      "atr": 1.48,
      "atr_percent": 2.57,
      "last_volume": 1790400,
      "avg_volume_14d": 2366271
    },
    {
      "symbol": "TSCO",
      "last_close": 54.63,
      "sma150": 55.39,
      "distance_percent": -1.36,
      "atr": 1.49,
      "atr_percent": 2.74,
      "last_volume": 3594900,
      "avg_volume_14d": 6201014
    },
    {
      "symbol": "SGHC",
      "last_close": 10.93,
      "sma150": 11.09,
      "distance_percent": -1.42,
      "atr": 0.61,
      "atr_percent": 5.08,
      "last_volume": 6603700,
      "avg_volume_14d": 2355442
    },
    {
      "symbol": "RGA",
      "last_close": 190.76,
      "sma150": 193.54,
      "distance_percent": -1.44,
      "atr": 3.95,
      "atr_percent": 2.1,
      "last_volume": 313800,
      "avg_volume_14d": 357050
    },
    {
      "symbol": "BB",
      "last_close": 4.07,
      "sma150": 4.13,
      "distance_percent": -1.46,
      "atr": 0.15,
      "atr_percent": 3.48,
      "last_volume": 8346400,
      "avg_volume_14d": 8391871
    },
    {
      "symbol": "AROC",
      "last_close": 24.11,
      "sma150": 24.47,
      "distance_percent": -1.46,
      "atr": 0.83,
      "atr_percent": 3.48,
      "last_volume": 1568000,
      "avg_volume_14d": 1642207
    },
    {
      "symbol": "EBAY",
      "last_close": 82.49,
      "sma150": 83.74,
      "distance_percent": -1.49,
      "atr": 2.2,
      "atr_percent": 2.64,
      "last_volume": 3015200,
      "avg_volume_14d": 4633335
    },
    {
      "symbol": "SYY",
      "last_close": 75.9,
      "sma150": 77.05,
      "distance_percent": -1.5,
      "atr": 1.3,
      "atr_percent": 1.72,
      "last_volume": 3219600,
      "avg_volume_14d": 3107385
    },
    {
      "symbol": "RNST",
      "last_close": 35.58,
      "sma150": 36.12,
      "distance_percent": -1.5,
      "atr": 0.81,
      "atr_percent": 2.36,
      "last_volume": 931000,
      "avg_volume_14d": 454857
    },
    {
      "symbol": "KMI",
      "last_close": 26.95,
      "sma150": 27.37,
      "distance_percent": -1.55,
      "atr": 0.53,
      "atr_percent": 1.95,
      "last_volume": 10978200,
      "avg_volume_14d": 15132378
    },
    {
      "symbol": "TRN",
      "last_close": 26.47,
      "sma150": 26.89,
      "distance_percent": -1.57,
      "atr": 0.64,
      "atr_percent": 2.5,
      "last_volume": 659300,
      "avg_volume_14d": 604657
    },
    {
      "symbol": "PFH",
      "last_close": 17.44,
      "sma150": 17.72,
      "distance_percent": -1.58,
      "atr": 0.21,
      "atr_percent": 1.18,
      "last_volume": 49800,
      "avg_volume_14d": 30528
    },
    {
      "symbol": "DTG",
      "last_close": 17.44,
      "sma150": 17.72,
      "distance_percent": -1.6,
      "atr": 0.22,
      "atr_percent": 1.25,
      "last_volume": 19700,
      "avg_volume_14d": 29014
    },
    {
      "symbol": "AAP",
      "last_close": 51.49,
      "sma150": 52.36,
      "distance_percent": -1.66,
      "atr": 2.3,
      "atr_percent": 4.59,
      "last_volume": 1299000,
      "avg_volume_14d": 1306035
    },
    {
      "symbol": "MSFT",
      "last_close": 485.5,
      "sma150": 494.25,
      "distance_percent": -1.77,
      "atr": 11.08,
      "atr_percent": 2.24,
      "last_volume": 25697600,
      "avg_volume_14d": 26644800
    },
    {
      "symbol": "CCK",
      "last_close": 96.93,
      "sma150": 98.74,
      "distance_percent": -1.84,
      "atr": 2.46,
      "atr_percent": 2.53,
      "last_volume": 1814300,
      "avg_volume_14d": 2417492
    },
    {
      "symbol": "AM",
      "last_close": 17.79,
      "sma150": 18.12,
      "distance_percent": -1.84,
      "atr": 0.35,
      "atr_percent": 1.97,
      "last_volume": 1326000,
      "avg_volume_14d": 2453471
    },
    {
      "symbol": "RJF",
      "last_close": 155.75,
      "sma150": 158.8,
      "distance_percent": -1.92,
      "atr": 3.92,
      "atr_percent": 2.48,
      "last_volume": 769600,
      "avg_volume_14d": 1197978
    },
    {
      "symbol": "ABT",
      "last_close": 128.54,
      "sma150": 131.11,
      "distance_percent": -1.96,
      "atr": 2.77,
      "atr_percent": 2.16,
      "last_volume": 5473800,
      "avg_volume_14d": 7349942
    },
    {
      "symbol": "CFR",
      "last_close": 124.64,
      "sma150": 127.21,
      "distance_percent": -2.02,
      "atr": 2.59,
      "atr_percent": 2.1,
      "last_volume": 378300,
      "avg_volume_14d": 477478
    },
    {
      "symbol": "SYK",
      "last_close": 372.29,
      "sma150": 380.11,
      "distance_percent": -2.06,
      "atr": 7.51,
      "atr_percent": 2.06,
      "last_volume": 2021100,
      "avg_volume_14d": 1868071
    },
    {
      "symbol": "TRU",
      "last_close": 84.88,
      "sma150": 86.66,
      "distance_percent": -2.06,
      "atr": 2.34,
      "atr_percent": 2.85,
      "last_volume": 1081700,
      "avg_volume_14d": 1874157
    },
    {
      "symbol": "MC",
      "last_close": 64.25,
      "sma150": 65.65,
      "distance_percent": -2.13,
      "atr": 1.97,
      "atr_percent": 3.13,
      "last_volume": 780400,
      "avg_volume_14d": 783535
    },
    {
      "symbol": "GGG",
      "last_close": 82.31,
      "sma150": 84.2,
      "distance_percent": -2.24,
      "atr": 1.51,
      "atr_percent": 1.86,
      "last_volume": 776600,
      "avg_volume_14d": 979178
    },
    {
      "symbol": "NNN",
      "last_close": 41.08,
      "sma150": 42.03,
      "distance_percent": -2.25,
      "atr": 0.57,
      "atr_percent": 1.4,
      "last_volume": 926900,
      "avg_volume_14d": 1306442
    },
    {
      "symbol": "DTW",
      "last_close": 21.47,
      "sma150": 21.98,
      "distance_percent": -2.3,
      "atr": 0.26,
      "atr_percent": 1.18,
      "last_volume": 26300,
      "avg_volume_14d": 22978
    },
    {
      "symbol": "SO",
      "last_close": 90.24,
      "sma150": 92.38,
      "distance_percent": -2.32,
      "atr": 1.19,
      "atr_percent": 1.32,
      "last_volume": 3490300,
      "avg_volume_14d": 5511028
    },
    {
      "symbol": "URI",
      "last_close": 814.97,
      "sma150": 835.51,
      "distance_percent": -2.46,
      "atr": 22.36,
      "atr_percent": 2.72,
      "last_volume": 787000,
      "avg_volume_14d": 689721
    },
    {
      "symbol": "WEX",
      "last_close": 148.66,
      "sma150": 152.44,
      "distance_percent": -2.48,
      "atr": 4.51,
      "atr_percent": 3.15,
      "last_volume": 300600,
      "avg_volume_14d": 473564
    },
    {
      "symbol": "EHC",
      "last_close": 116.25,
      "sma150": 119.28,
      "distance_percent": -2.54,
      "atr": 2.34,
      "atr_percent": 2.05,
      "last_volume": 519500,
      "avg_volume_14d": 659492
    },
    {
      "symbol": "HTGC",
      "last_close": 17.88,
      "sma150": 18.35,
      "distance_percent": -2.57,
      "atr": 0.29,
      "atr_percent": 1.67,
      "last_volume": 980000,
      "avg_volume_14d": 1395614
    },
    {
      "symbol": "RMD",
      "last_close": 255.04,
      "sma150": 261.86,
      "distance_percent": -2.61,
      "atr": 5.49,
      "atr_percent": 2.2,
      "last_volume": 606000,
      "avg_volume_14d": 1221728
    },
    {
      "symbol": "RDY",
      "last_close": 13.99,
      "sma150": 14.37,
      "distance_percent": -2.66,
      "atr": 0.19,
      "atr_percent": 1.35,
      "last_volume": 1017700,
      "avg_volume_14d": 985885
    },
    {
      "symbol": "BLK",
      "last_close": 1040.06,
      "sma150": 1069.95,
      "distance_percent": -2.79,
      "atr": 22.78,
      "atr_percent": 2.18,
      "last_volume": 560500,
      "avg_volume_14d": 655142
    },
    {
      "symbol": "TFII",
      "last_close": 86.79,
      "sma150": 89.3,
      "distance_percent": -2.82,
      "atr": 2.32,
      "atr_percent": 2.73,
      "last_volume": 1201500,
      "avg_volume_14d": 175971
    },
    {
      "symbol": "BRSL",
      "last_close": 15.65,
      "sma150": 16.1,
      "distance_percent": -2.82,
      "atr": 0.34,
      "atr_percent": 2.13,
      "last_volume": 1997000,
      "avg_volume_14d": 1818678
    },
    {
      "symbol": "HMC",
      "last_close": 30.3,
      "sma150": 31.18,
      "distance_percent": -2.82,
      "atr": 0.35,
      "atr_percent": 1.18,
      "last_volume": 985400,
      "avg_volume_14d": 1016728
    },
    {
      "symbol": "KKRS",
      "last_close": 17.44,
      "sma150": 17.96,
      "distance_percent": -2.88,
      "atr": 0.23,
      "atr_percent": 1.31,
      "last_volume": 22500,
      "avg_volume_14d": 42150
    },
    {
      "symbol": "BEN",
      "last_close": 22.52,
      "sma150": 23.21,
      "distance_percent": -2.98,
      "atr": 0.62,
      "atr_percent": 2.79,
      "last_volume": 3698100,
      "avg_volume_14d": 5448535
    },
    {
      "symbol": "MET",
      "last_close": 76.33,
      "sma150": 78.68,
      "distance_percent": -2.99,
      "atr": 1.74,
      "atr_percent": 2.27,
      "last_volume": 2552700,
      "avg_volume_14d": 4443571
    },
    {
      "symbol": "ETN",
      "last_close": 341.69,
      "sma150": 352.35,
      "distance_percent": -3.03,
      "atr": 12.22,
      "atr_percent": 3.5,
      "last_volume": 2474500,
      "avg_volume_14d": 3090935
    },
    {
      "symbol": "TDG",
      "last_close": 1355.01,
      "sma150": 1397.96,
      "distance_percent": -3.07,
      "atr": 33.34,
      "atr_percent": 2.51,
      "last_volume": 239100,
      "avg_volume_14d": 356128
    },
    {
      "symbol": "PRI",
      "last_close": 258.17,
      "sma150": 266.6,
      "distance_percent": -3.16,
      "atr": 5.98,
      "atr_percent": 2.32,
      "last_volume": 164000,
      "avg_volume_14d": 215471
    },
    {
      "symbol": "CAE",
      "last_close": 26.45,
      "sma150": 27.32,
      "distance_percent": -3.19,
      "atr": 0.76,
      "atr_percent": 2.89,
      "last_volume": 550200,
      "avg_volume_14d": 634100
    },
    {
      "symbol": "SXT",
      "last_close": 97.65,
      "sma150": 100.88,
      "distance_percent": -3.2,
      "atr": 2.1,
      "atr_percent": 2.22,
      "last_volume": 465300,
      "avg_volume_14d": 300278
    },
    {
      "symbol": "KIM",
      "last_close": 20.62,
      "sma150": 21.32,
      "distance_percent": -3.26,
      "atr": 0.34,
      "atr_percent": 1.65,
      "last_volume": 3475700,
      "avg_volume_14d": 5142571
    },
    {
      "symbol": "IPG",
      "last_close": 24.57,
      "sma150": 25.4,
      "distance_percent": -3.26,
      "atr": 0.63,
      "atr_percent": 2.5,
      "last_volume": 82081300,
      "avg_volume_14d": 7060378
    },
    {
      "symbol": "NFG",
      "last_close": 81.65,
      "sma150": 84.46,
      "distance_percent": -3.32,
      "atr": 1.51,
      "atr_percent": 1.87,
      "last_volume": 483800,
      "avg_volume_14d": 565714
    },
    {
      "symbol": "AMBP",
      "last_close": 3.75,
      "sma150": 3.88,
      "distance_percent": -3.35,
      "atr": 0.1,
      "atr_percent": 2.63,
      "last_volume": 812100,
      "avg_volume_14d": 1298507
    },
    {
      "symbol": "ADT",
      "last_close": 8.16,
      "sma150": 8.45,
      "distance_percent": -3.44,
      "atr": 0.17,
      "atr_percent": 2.07,
      "last_volume": 7090900,
      "avg_volume_14d": 7556235
    },
    {
      "symbol": "SUZ",
      "last_close": 8.96,
      "sma150": 9.29,
      "distance_percent": -3.52,
      "atr": 0.17,
      "atr_percent": 1.85,
      "last_volume": 1966700,
      "avg_volume_14d": 2887385
    },
    {
      "symbol": "BDC",
      "last_close": 113.75,
      "sma150": 117.93,
      "distance_percent": -3.55,
      "atr": 3.46,
      "atr_percent": 3.07,
      "last_volume": 159400,
      "avg_volume_14d": 259350
    },
    {
      "symbol": "CTVA",
      "last_close": 66.65,
      "sma150": 69.1,
      "distance_percent": -3.55,
      "atr": 1.42,
      "atr_percent": 2.18,
      "last_volume": 2062300,
      "avg_volume_14d": 3797714
    },
    {
      "symbol": "AOS",
      "last_close": 66.33,
      "sma150": 68.78,
      "distance_percent": -3.56,
      "atr": 1.31,
      "atr_percent": 2.01,
      "last_volume": 2339100,
      "avg_volume_14d": 1285514
    },
    {
      "symbol": "J",
      "last_close": 135.86,
      "sma150": 140.89,
      "distance_percent": -3.57,
      "atr": 5.13,
      "atr_percent": 3.53,
      "last_volume": 1238100,
      "avg_volume_14d": 1326857
    },
    {
      "symbol": "MSA",
      "last_close": 160.96,
      "sma150": 166.93,
      "distance_percent": -3.57,
      "atr": 3.35,
      "atr_percent": 2.12,
      "last_volume": 296900,
      "avg_volume_14d": 197785
    },
    {
      "symbol": "MAS",
      "last_close": 64.42,
      "sma150": 66.83,
      "distance_percent": -3.6,
      "atr": 1.4,
      "atr_percent": 2.29,
      "last_volume": 2880400,
      "avg_volume_14d": 2627985
    },
    {
      "symbol": "SPGI",
      "last_close": 495.61,
      "sma150": 514.9,
      "distance_percent": -3.75,
      "atr": 7.74,
      "atr_percent": 1.57,
      "last_volume": 1041700,
      "avg_volume_14d": 1597121
    },
    {
      "symbol": "V",
      "last_close": 333.79,
      "sma150": 347.3,
      "distance_percent": -3.89,
      "atr": 5.73,
      "atr_percent": 1.73,
      "last_volume": 4309100,
      "avg_volume_14d": 6765185
    },
    {
      "symbol": "CXT",
      "last_close": 56.25,
      "sma150": 58.55,
      "distance_percent": -3.92,
      "atr": 1.79,
      "atr_percent": 3.09,
      "last_volume": 381200,
      "avg_volume_14d": 443178
    },
    {
      "symbol": "DE",
      "last_close": 469.87,
      "sma150": 489.29,
      "distance_percent": -3.97,
      "atr": 10.6,
      "atr_percent": 2.22,
      "last_volume": 5471700,
      "avg_volume_14d": 1422507
    },
    {
      "symbol": "MA",
      "last_close": 544.93,
      "sma150": 567.6,
      "distance_percent": -3.99,
      "atr": 9.51,
      "atr_percent": 1.75,
      "last_volume": 2184700,
      "avg_volume_14d": 2876600
    }
  ],
  "failed_tickers": [],
  "filtered_by_sma": [
    "A",
    "AA",
    "ABBV",
    "ABCB",
    "ABEV",
    "ABM",
    "ABR",
    "ACA",
    "ACHR",
    "ACI",
    "ACM",
    "ACN",
    "AD",
    "ADC",
    "ADM",
    "AEE",
    "AEG",
    "AEM",
    "AEO",
    "AER",
    "AES",
    "AFG",
    "AG",
    "AGI",
    "AGO",
    "AGX",
    "AHR",
    "AI",
    "AIG",
    "AIR",
    "AIZ",
    "AJG",
    "AKR",
    "AL",
    "ALB",
    "ALC",
    "ALG",
    "ALK",
    "ALL",
    "ALLE",
    "ALLY",
    "ALSN",
    "AMCR",
    "AME",
    "AMG",
    "AMH",
    "AMP",
    "AMR",
    "AMRC",
    "AMT",
    "AMTM",
    "AMX",
    "AN",
    "ANET",
    "ANF",
    "AON",
    "APAM",
    "APD",
    "APG",
    "APH",
    "APO",
    "AQN",
    "ARDT",
    "ARE",
    "ARES",
    "ARMK",
    "ARW",
    "AS",
    "ASAN",
    "ASB",
    "ASGN",
    "ASR",
    "ASX",
    "ATGE",
    "ATHM",
    "ATI",
    "ATMU",
    "ATO",
    "ATR",
    "ATS",
    "AU",
    "AUB",
    "AVA",
    "AVAL",
    "AVB",
    "AVNT",
    "AVTR",
    "AWI",
    "AWK",
    "AWR",
    "AXP",
    "AXS",
    "AXTA",
    "AYI",
    "B",
    "BA",
    "BABA",
    "BAC",
    "BAH",
    "BALL",
    "BAM",
    "BANC",
    "BAP",
    "BAX",
    "BBAI",
    "BBD",
    "BBDO",
    "BBU",
    "BBUC",
    "BBVA",
    "BBWI",
    "BBY",
    "BC",
    "BCC",
    "BCH",
    "BCO",
    "BCS",
    "BDX",
    "BE",
    "BEKE",
    "BEP",
    "BEPC",
    "BFAM",
    "BFH",
    "BG",
    "BHP",
    "BILL",
    "BIO",
    "BIP",
    "BIPC",
    "BIPJ",
    "BIRK",
    "BJ",
    "BK",
    "BKD",
    "BKE",
    "BKH",
    "BKU",
    "BLCO",
    "BLD",
    "BLDR",
    "BMA",
    "BMI",
    "BMO",
    "BMY",
    "BN",
    "BNS",
    "BNT",
    "BOOT",
    "BOX",
    "BP",
    "BR",
    "BRBR",
    "BRC",
    "BRO",
    "BROS",
    "BSAC",
    "BSBR",
    "BSM",
    "BTI",
    "BTU",
    "BUD",
    "BUR",
    "BVN",
    "BWA",
    "BWNB",
    "BWSN",
    "BWXT",
    "BX",
    "C",
    "CAAP",
    "CACI",
    "CADE",
    "CAG",
    "CAH",
    "CARR",
    "CAT",
    "CAVA",
    "CB",
    "CBRE",
    "CBT",
    "CBZ",
    "CC",
    "CCI",
    "CCJ",
    "CCL",
    "CDE",
    "CDP",
    "CE",
    "CF",
    "CFG",
    "CGAU",
    "CHD",
    "CHE",
    "CHH",
    "CHT",
    "CHWY",
    "CI",
    "CIB",
    "CIEN",
    "CIG",
    "CII",
    "CIVI",
    "CL",
    "CLF",
    "CLS",
    "CLVT",
    "CLX",
    "CM",
    "CMA",
    "CMBT",
    "CMC",
    "CMCM",
    "CMG",
    "CMI",
    "CMPO",
    "CMS",
    "CNA",
    "CNC",
    "CNH",
    "CNI",
    "CNK",
    "CNM",
    "CNO",
    "CNP",
    "CNQ",
    "CNS",
    "CNX",
    "COHR",
    "COLD",
    "COMP",
    "CON",
    "COP",
    "COR",
    "COTY",
    "CP",
    "CPA",
    "CPAY",
    "CPK",
    "CPNG",
    "CPRI",
    "CPT",
    "CQP",
    "CRBG",
    "CRH",
    "CRK",
    "CRL",
    "CRM",
    "CRS",
    "CSAN",
    "CSL",
    "CSTM",
    "CSW",
    "CTRA",
    "CTRE",
    "CUBE",
    "CUBI",
    "CUK",
    "CURB",
    "CUZ",
    "CVE",
    "CVI",
    "CVNA",
    "CVS",
    "CW",
    "CWAN",
    "CWEN",
    "CWK",
    "CWT",
    "CX",
    "D",
    "DAL",
    "DAN",
    "DAR",
    "DAY",
    "DB",
    "DBD",
    "DBRG",
    "DCI",
    "DD",
    "DDS",
    "DECK",
    "DEI",
    "DELL",
    "DEO",
    "DFH",
    "DGX",
    "DHI",
    "DHR",
    "DINO",
    "DIS",
    "DK",
    "DKL",
    "DLB",
    "DLR",
    "DOC",
    "DOCN",
    "DOCS",
    "DOV",
    "DOW",
    "DRD",
    "DRI",
    "DT",
    "DTM",
    "DVA",
    "DVN",
    "DXC",
    "DY",
    "E",
    "EAT",
    "EBR",
    "EC",
    "ECG",
    "ED",
    "EFX",
    "EG",
    "EGO",
    "EGP",
    "EIX",
    "EL",
    "ELAN",
    "ELF",
    "ELP",
    "ELPC",
    "ELS",
    "ELV",
    "EMA",
    "EME",
    "EMN",
    "ENIC",
    "ENS",
    "ENVA",
    "EOG",
    "EPAC",
    "EPAM",
    "EPR",
    "EPRT",
    "EQH",
    "EQNR",
    "EQR",
    "EQT",
    "ERJ",
    "ERO",
    "ESAB",
    "ESE",
    "ESI",
    "ESNT",
    "ESS",
    "ESTC",
    "ET",
    "ETR",
    "ETSY",
    "EVR",
    "EW",
    "EXK",
    "EXP",
    "EXPD",
    "EXR",
    "F",
    "FAF",
    "FBIN",
    "FBK",
    "FBP",
    "FCPT",
    "FDX",
    "FE",
    "FERG",
    "FG",
    "FHI",
    "FHN",
    "FI",
    "FICO",
    "FIHL",
    "FIS",
    "FIX",
    "FLO",
    "FLR",
    "FLS",
    "FLUT",
    "FMC",
    "FMS",
    "FMX",
    "FN",
    "FNB",
    "FND",
    "FNF",
    "FNV",
    "FOUR",
    "FR",
    "FRO",
    "FSK",
    "FSM",
    "FTI",
    "FTS",
    "FTV",
    "FUN",
    "G",
    "GAP",
    "GBCI",
    "GBTG",
    "GD",
    "GDDY",
    "GE",
    "GEF",
    "GENI",
    "GEO",
    "GEV",
    "GFI",
    "GFL",
    "GGB",
    "GHC",
    "GIB",
    "GIL",
    "GIS",
    "GKOS",
    "GLOB",
    "GLW",
    "GM",
    "GME",
    "GMED",
    "GNRC",
    "GNW",
    "GOLF",
    "GPI",
    "GPK",
    "GPN",
    "GPOR",
    "GRBK",
    "GRMN",
    "GRND",
    "GS",
    "GSK",
    "GTES",
    "GTLS",
    "GVA",
    "GWRE",
    "GWW",
    "H",
    "HAE",
    "HAFN",
    "HAL",
    "HASI",
    "HAYW",
    "HBI",
    "HBM",
    "HCA",
    "HCC",
    "HCI",
    "HD",
    "HESM",
    "HGTY",
    "HHH",
    "HI",
    "HIG",
    "HII",
    "HIMS",
    "HIW",
    "HL",
    "HLI",
    "HLN",
    "HLT",
    "HMY",
    "HNI",
    "HOG",
    "HP",
    "HPQ",
    "HR",
    "HRB",
    "HRI",
    "HRL",
    "HSBC",
    "HSY",
    "HTH",
    "HUBS",
    "HUM",
    "HWM",
    "HXL",
    "IAG",
    "IBM",
    "IBN",
    "IBP",
    "ICE",
    "ICL",
    "IDA",
    "IFF",
    "IFS",
    "IHG",
    "IHS",
    "INFA",
    "ING",
    "INGM",
    "INGR",
    "INSP",
    "INSW",
    "INVH",
    "IOT",
    "IP",
    "IQV",
    "IRM",
    "IRT",
    "IT",
    "ITGR",
    "ITT",
    "ITUB",
    "IVZ",
    "IX",
    "JBTM",
    "JCI",
    "JHG",
    "JHX",
    "JLL",
    "JNJ",
    "JOBY",
    "JOE",
    "JPM",
    "JXN",
    "KAI",
    "KB",
    "KBH",
    "KBR",
    "KD",
    "KEN",
    "KEP",
    "KEX",
    "KEY",
    "KEYS",
    "KFY",
    "KGC",
    "KKR",
    "KMPR",
    "KMX",
    "KN",
    "KNF",
    "KNSL",
    "KNTK",
    "KNX",
    "KO",
    "KOF",
    "KR",
    "KRC",
    "KRMN",
    "KT",
    "KVUE",
    "KVYO",
    "KWR",
    "L",
    "LAC",
    "LB",
    "LCII",
    "LDOS",
    "LEA",
    "LEN",
    "LEVI",
    "LII",
    "LLY",
    "LMND",
    "LMT",
    "LNC",
    "LNG",
    "LOAR",
    "LPL",
    "LPX",
    "LRN",
    "LTH",
    "LTM",
    "LU",
    "LUMN",
    "LUV",
    "LVS",
    "LW",
    "LXP",
    "LYB",
    "LYG",
    "LYV",
    "M",
    "MAA",
    "MAIN",
    "MANU",
    "MCD",
    "MCK",
    "MCY",
    "MDT",
    "MDU",
    "MFC",
    "MFG",
    "MGA",
    "MHO",
    "MIR",
    "MKC",
    "MKL",
    "MLI",
    "MLM",
    "MMC",
    "MMM",
    "MMS",
    "MNSO",
    "MO",
    "MOD",
    "MOH",
    "MOS",
    "MP",
    "MPC",
    "MPLX",
    "MPW",
    "MRK",
    "MS",
    "MSGE",
    "MSGS",
    "MSI",
    "MT",
    "MTD",
    "MTDR",
    "MTG",
    "MTH",
    "MTN",
    "MTRN",
    "MTZ",
    "MUFG",
    "MUR",
    "MUSA",
    "MWA",
    "NATL",
    "NCLH",
    "NE",
    "NEE",
    "NEM",
    "NEU",
    "NGG",
    "NGVT",
    "NHI",
    "NI",
    "NJR",
    "NKE",
    "NLY",
    "NMR",
    "NNI",
    "NOG",
    "NOK",
    "NOV",
    "NOW",
    "NPO",
    "NRG",
    "NSA",
    "NSC",
    "NU",
    "NUE",
    "NVO",
    "NVS",
    "NVST",
    "NVT",
    "NWG",
    "NXE",
    "NYT",
    "OBDC",
    "OC",
    "OGN",
    "OGS",
    "OHI",
    "OII",
    "OKE",
    "OKLO",
    "OLN",
    "OMC",
    "OMF",
    "ONON",
    "ONTO",
    "OR",
    "ORA",
    "ORCL",
    "ORI",
    "OSCR",
    "OSK",
    "OTIS",
    "OUT",
    "OWL",
    "OXY",
    "PAAS",
    "PAG",
    "PAGS",
    "PAM",
    "PATH",
    "PAYC",
    "PBF",
    "PBH",
    "PCG",
    "PCOR",
    "PDI",
    "PEN",
    "PFE",
    "PFS",
    "PFSI",
    "PG",
    "PGR",
    "PH",
    "PHG",
    "PHI",
    "PHIN",
    "PHM",
    "PII",
    "PINS",
    "PIPR",
    "PKX",
    "PL",
    "PLD",
    "PLNT",
    "PM",
    "PNW",
    "POR",
    "POST",
    "PPG",
    "PR",
    "PRGO",
    "PRIM",
    "PRKS",
    "PRM",
    "PRMB",
    "PSA",
    "PSN",
    "PSO",
    "PSTG",
    "PSX",
    "PUK",
    "PVH",
    "PWR",
    "QBTS",
    "QS",
    "QSR",
    "QTWO",
    "QXO",
    "RACE",
    "RBA",
    "RBC",
    "RBLX",
    "RBRK",
    "RCB",
    "RCI",
    "RCL",
    "RDDT",
    "RELX",
    "REVG",
    "REXR",
    "REZI",
    "RF",
    "RH",
    "RHI",
    "RIG",
    "RIO",
    "RKT",
    "RL",
    "RLI",
    "RLX",
    "RNR",
    "ROK",
    "ROL",
    "RPM",
    "RS",
    "RSG",
    "RSI",
    "RTO",
    "RTX",
    "RVTY",
    "RXO",
    "RY",
    "RYAN",
    "RYN",
    "S",
    "SA",
    "SAH",
    "SAM",
    "SAN",
    "SAND",
    "SAP",
    "SARO",
    "SBS",
    "SBSW",
    "SCCO",
    "SE",
    "SEE",
    "SEI",
    "SF",
    "SFBS",
    "SGI",
    "SHAK",
    "SHG",
    "SID",
    "SIG",
    "SII",
    "SITE",
    "SJM",
    "SKE",
    "SKM",
    "SKT",
    "SKY",
    "SLF",
    "SLG",
    "SLGN",
    "SM",
    "SMFG",
    "SMG",
    "SMR",
    "SN",
    "SNA",
    "SNAP",
    "SNDR",
    "SNOW",
    "SNX",
    "SOJD",
    "SOLV",
    "SON",
    "SONY",
    "SPG",
    "SPHR",
    "SPNT",
    "SPOT",
    "SPR",
    "SPXC",
    "SQM",
    "SR",
    "SRE",
    "SSB",
    "SSL",
    "ST",
    "STAG",
    "STE",
    "STLA",
    "STM",
    "STN",
    "STNG",
    "STT",
    "STVN",
    "STWD",
    "STZ",
    "SU",
    "SUN",
    "SVV",
    "SW",
    "SWX",
    "SXI",
    "SYF",
    "T",
    "TAC",
    "TAK",
    "TAP",
    "TBB",
    "TBBB",
    "TD",
    "TDC",
    "TDS",
    "TDW",
    "TDY",
    "TECK",
    "TEF",
    "TEL",
    "TEO",
    "TEVA",
    "TEX",
    "TFC",
    "TFPM",
    "TFX",
    "TGLS",
    "TGNA",
    "TGS",
    "TGT",
    "THC",
    "THG",
    "THO",
    "TIC",
    "TIMB",
    "TJX",
    "TKC",
    "TKO",
    "TKR",
    "TLK",
    "TM",
    "TME",
    "TMO",
    "TNET",
    "TNL",
    "TOL",
    "TOST",
    "TPC",
    "TPH",
    "TPL",
    "TPR",
    "TREX",
    "TRGP",
    "TRNO",
    "TRP",
    "TRV",
    "TS",
    "TSLX",
    "TSM",
    "TSN",
    "TTAM",
    "TTC",
    "TTE",
    "TU",
    "TV",
    "TWLO",
    "TX",
    "TXT",
    "TYL",
    "U",
    "UAA",
    "UBER",
    "UDR",
    "UGI",
    "UGP",
    "UHAL",
    "UHS",
    "UI",
    "UL",
    "ULS",
    "UNF",
    "UNFI",
    "UNH",
    "UNMA",
    "UPS",
    "USAC",
    "USB",
    "UWMC",
    "VAC",
    "VAL",
    "VALE",
    "VEEV",
    "VFC",
    "VG",
    "VICI",
    "VIK",
    "VIPS",
    "VIRT",
    "VIST",
    "VIV",
    "VLO",
    "VMC",
    "VMI",
    "VNO",
    "VNT",
    "VRT",
    "VSCO",
    "VSH",
    "VST",
    "VTMX",
    "VTR",
    "VVV",
    "W",
    "WAB",
    "WAT",
    "WBS",
    "WCC",
    "WCN",
    "WD",
    "WDS",
    "WELL",
    "WF",
    "WFC",
    "WFG",
    "WH",
    "WHR",
    "WIT",
    "WK",
    "WLK",
    "WLYB",
    "WM",
    "WMS",
    "WMT",
    "WNS",
    "WOR",
    "WPM",
    "WPP",
    "WRB",
    "WRBY",
    "WSO",
    "WST",
    "WTM",
    "WTRG",
    "WTS",
    "WU",
    "WWW",
    "WY",
    "XPO",
    "XYZ",
    "YELP",
    "YETI",
    "YMM",
    "YOU",
    "YPF",
    "YUM",
    "YUMC",
    "ZBH",
    "ZETA",
    "ZGN",
    "ZK",
    "ZTO",
    "ZTS",
    "ZWS",
    "VRNS",
    "ADBE",
    "AMD",
    "ABNB",
    "AKAM",
    "ALGN",
    "LNT",
    "GOOGL",
    "GOOG",
    "AEP",
    "AMGN",
    "ADI",
    "APA",
    "AAPL",
    "AMAT",
    "APP",
    "ACGL",
    "ADP",
    "AXON",
    "BKR",
    "TECH",
    "BIIB",
    "BKNG",
    "AVGO",
    "CHRW",
    "CDNS",
    "CPB",
    "CBOE",
    "CDW",
    "CHTR",
    "CINF",
    "CTAS",
    "CSCO",
    "CTSH",
    "COIN",
    "CMCSA",
    "CEG",
    "COO",
    "CPRT",
    "CSGP",
    "COST",
    "CRWD",
    "CSX",
    "DDOG",
    "DXCM",
    "FANG",
    "DLTR",
    "DPZ",
    "DASH",
    "EA",
    "EQIX",
    "ERIE",
    "EVRG",
    "EXC",
    "EXE",
    "EXPE",
    "FFIV",
    "FDS",
    "FAST",
    "FSLR",
    "FTNT",
    "FOXA",
    "FOX",
    "GEHC",
    "GEN",
    "GILD",
    "HAS",
    "HSIC",
    "HOLX",
    "HON",
    "HST",
    "IDXX",
    "INCY",
    "PODD",
    "INTC",
    "IBKR",
    "INTU",
    "ISRG",
    "JBHT",
    "JKHY",
    "KDP",
    "KMB",
    "KLAC",
    "KHC",
    "LRCX",
    "LIN",
    "LKQ",
    "LULU",
    "MAR",
    "META",
    "MCHP",
    "MU",
    "MRNA",
    "MDLZ",
    "MPWR",
    "MNST",
    "NFLX",
    "NWSA",
    "NWS",
    "NDSN",
    "NTRS",
    "NVDA",
    "NXPI",
    "ORLY",
    "ODFL",
    "PCAR",
    "PLTR",
    "PANW",
    "PSKY",
    "PAYX",
    "PYPL",
    "PEP",
    "POOL",
    "PFG",
    "PTC",
    "REGN",
    "HOOD",
    "ROP",
    "ROST",
    "SBAC",
    "STX",
    "SWKS",
    "STLD",
    "SMCI",
    "SNPS",
    "TMUS",
    "TER",
    "TSLA",
    "TXN",
    "TTD",
    "TRMB",
    "ULTA",
    "UAL",
    "VRSN",
    "VRSK",
    "VZ",
    "VRTX",
    "VTRS",
    "WBD",
    "WDC",
    "WDAY",
    "WYNN",
    "XEL",
    "ZBRA"
  ],
  "summary": {
    "hot_stocks_count": 150,
    "watch_list_count": 118,
    "failed_count": 0,
    "filtered_by_sma_count": 1140,
    "total_analyzed": 1761
  }
}